<?xml version="1.0" encoding="UTF-8"?>

<!-- generated on 2023-08-06 16:22:54 by Eclipse SUMO GUI Version 1.18.0
<configuration xmlns:xsi="http://www.w3.org/2001/XMLSchema-instance" xsi:noNamespaceSchemaLocation="http://sumo.dlr.de/xsd/sumoConfiguration.xsd">

    <input>
        <net-file value="/home/arms04/autonomous_driving_stack/Intelligent_Intersection_management/Li_and_Liu/cfg/my_network.net.xml"/>
        <route-files value="/home/arms04/autonomous_driving_stack/Intelligent_Intersection_management/Li_and_Liu/cfg/my_route.rou.xml"/>
    </input>

    <output>
        <tripinfo-output value="/home/arms04/autonomous_driving_stack/Intelligent_Intersection_management/Li_and_Liu/p.xml"/>
    </output>

    <time>
        <step-length value="0.01"/>
    </time>

    <processing>
        <lateral-resolution value="3"/>
    </processing>

    <report>
        <duration-log.statistics value="true"/>
    </report>

    <traci_server>
        <remote-port value="33247"/>
    </traci_server>

    <gui_only>
        <gui-settings-file value="/home/arms04/autonomous_driving_stack/Intelligent_Intersection_management/Li_and_Liu/cfg/my_gui.gui.xml"/>
        <start value="true"/>
    </gui_only>

</configuration>
-->

<tripinfos xmlns:xsi="http://www.w3.org/2001/XMLSchema-instance" xsi:noNamespaceSchemaLocation="http://sumo.dlr.de/xsd/tripinfo_file.xsd">
    <tripinfo id="v9.a_1" depart="27.01" departLane="a+_0" departPos="4.10" departPosLat="0.00" departSpeed="0.00" departDelay="0.00" arrival="70.90" arrivalLane="b-_0" arrivalPos="492.80" arrivalPosLat="0.00" arrivalSpeed="37.95" duration="43.89" routeLength="990.53" waitingTime="0.16" waitingCount="1" stopTime="0.00" timeLoss="-7.70" rerouteNo="0" devices="tripinfo_v9.a_1" vType="vtypeauto" speedFactor="2.71" vaporized=""/>
    <tripinfo id="v34.d_3" depart="102.01" departLane="d+_0" departPos="4.10" departPosLat="0.00" departSpeed="0.00" departDelay="0.00" arrival="146.16" arrivalLane="c-_0" arrivalPos="492.80" arrivalPosLat="0.00" arrivalSpeed="37.95" duration="44.15" routeLength="995.69" waitingTime="0.16" waitingCount="1" stopTime="0.00" timeLoss="-7.70" rerouteNo="0" devices="tripinfo_v34.d_3" vType="vtypeauto" speedFactor="2.71" vaporized=""/>
    <tripinfo id="v34.d_2" depart="104.17" departLane="d+_0" departPos="4.10" departPosLat="0.00" departSpeed="0.00" departDelay="2.16" arrival="148.41" arrivalLane="b-_0" arrivalPos="492.80" arrivalPosLat="0.00" arrivalSpeed="37.95" duration="44.24" routeLength="995.90" waitingTime="0.16" waitingCount="1" stopTime="0.00" timeLoss="-7.62" rerouteNo="0" devices="tripinfo_v34.d_2" vType="vtypeauto" speedFactor="2.71" vaporized=""/>
    <tripinfo id="v35.b_2" depart="105.01" departLane="b+_0" departPos="4.10" departPosLat="0.00" departSpeed="0.00" departDelay="0.00" arrival="149.17" arrivalLane="d-_0" arrivalPos="492.80" arrivalPosLat="0.00" arrivalSpeed="37.95" duration="44.16" routeLength="995.90" waitingTime="0.16" waitingCount="1" stopTime="0.00" timeLoss="-7.70" rerouteNo="0" devices="tripinfo_v35.b_2" vType="vtypeauto" speedFactor="2.71" vaporized=""/>
    <tripinfo id="v40.a_1" depart="120.01" departLane="a+_0" departPos="4.10" departPosLat="0.00" departSpeed="0.00" departDelay="0.00" arrival="163.90" arrivalLane="b-_0" arrivalPos="492.80" arrivalPosLat="0.00" arrivalSpeed="37.95" duration="43.89" routeLength="990.53" waitingTime="0.16" waitingCount="1" stopTime="0.00" timeLoss="-7.70" rerouteNo="0" devices="tripinfo_v40.a_1" vType="vtypeauto" speedFactor="2.71" vaporized=""/>
    <tripinfo id="v40.a_2" depart="122.17" departLane="a+_0" departPos="4.10" departPosLat="0.00" departSpeed="0.00" departDelay="2.16" arrival="166.41" arrivalLane="c-_0" arrivalPos="492.80" arrivalPosLat="0.00" arrivalSpeed="37.95" duration="44.24" routeLength="995.90" waitingTime="0.16" waitingCount="1" stopTime="0.00" timeLoss="-7.62" rerouteNo="0" devices="tripinfo_v40.a_2" vType="vtypeauto" speedFactor="2.71" vaporized=""/>
    <tripinfo id="v42.c_2" depart="126.01" departLane="c+_0" departPos="4.10" departPosLat="0.00" departSpeed="0.00" departDelay="0.00" arrival="172.03" arrivalLane="a-_0" arrivalPos="492.80" arrivalPosLat="0.00" arrivalSpeed="31.99" duration="46.02" routeLength="995.90" waitingTime="0.16" waitingCount="1" stopTime="0.00" timeLoss="-5.82" rerouteNo="0" devices="tripinfo_v42.c_2" vType="vtypeauto" speedFactor="2.29" vaporized=""/>
    <tripinfo id="v43.b_2" depart="129.01" departLane="b+_0" departPos="4.10" departPosLat="0.00" departSpeed="0.00" departDelay="0.00" arrival="177.68" arrivalLane="d-_0" arrivalPos="492.80" arrivalPosLat="0.00" arrivalSpeed="26.68" duration="48.67" routeLength="995.90" waitingTime="0.16" waitingCount="1" stopTime="0.00" timeLoss="-3.17" rerouteNo="0" devices="tripinfo_v43.b_2" vType="vtypeauto" speedFactor="1.91" vaporized=""/>
    <tripinfo id="v46.a_3" depart="138.01" departLane="a+_0" departPos="4.10" departPosLat="0.00" departSpeed="0.00" departDelay="0.00" arrival="182.51" arrivalLane="d-_0" arrivalPos="492.80" arrivalPosLat="0.00" arrivalSpeed="36.59" duration="44.50" routeLength="995.70" waitingTime="0.16" waitingCount="1" stopTime="0.00" timeLoss="-7.34" rerouteNo="0" devices="tripinfo_v46.a_3" vType="vtypeauto" speedFactor="2.61" vaporized=""/>
    <tripinfo id="v56.d_1" depart="168.01" departLane="d+_0" departPos="4.10" departPosLat="0.00" departSpeed="0.00" departDelay="0.00" arrival="211.90" arrivalLane="a-_0" arrivalPos="492.80" arrivalPosLat="0.00" arrivalSpeed="37.95" duration="43.89" routeLength="990.53" waitingTime="0.16" waitingCount="1" stopTime="0.00" timeLoss="-7.70" rerouteNo="0" devices="tripinfo_v56.d_1" vType="vtypeauto" speedFactor="2.71" vaporized=""/>
    <tripinfo id="v59.b_3" depart="177.01" departLane="b+_0" departPos="4.10" departPosLat="0.00" departSpeed="0.00" departDelay="0.00" arrival="221.51" arrivalLane="a-_0" arrivalPos="492.80" arrivalPosLat="0.00" arrivalSpeed="36.59" duration="44.50" routeLength="995.69" waitingTime="0.16" waitingCount="1" stopTime="0.00" timeLoss="-7.34" rerouteNo="0" devices="tripinfo_v59.b_3" vType="vtypeauto" speedFactor="2.61" vaporized=""/>
    <tripinfo id="v65.c_1" depart="195.01" departLane="c+_0" departPos="4.10" departPosLat="0.00" departSpeed="0.00" departDelay="0.00" arrival="238.90" arrivalLane="d-_0" arrivalPos="492.80" arrivalPosLat="0.00" arrivalSpeed="37.95" duration="43.89" routeLength="990.53" waitingTime="0.16" waitingCount="1" stopTime="0.00" timeLoss="-7.70" rerouteNo="0" devices="tripinfo_v65.c_1" vType="vtypeauto" speedFactor="2.71" vaporized=""/>
    <tripinfo id="v67.a_1" depart="201.01" departLane="a+_0" departPos="4.10" departPosLat="0.00" departSpeed="0.00" departDelay="0.00" arrival="244.90" arrivalLane="b-_0" arrivalPos="492.80" arrivalPosLat="0.00" arrivalSpeed="37.95" duration="43.89" routeLength="990.53" waitingTime="0.16" waitingCount="1" stopTime="0.00" timeLoss="-7.70" rerouteNo="0" devices="tripinfo_v67.a_1" vType="vtypeauto" speedFactor="2.71" vaporized=""/>
    <tripinfo id="v78.c_3" depart="234.01" departLane="c+_0" departPos="4.10" departPosLat="0.00" departSpeed="0.00" departDelay="0.00" arrival="278.16" arrivalLane="b-_0" arrivalPos="492.80" arrivalPosLat="0.00" arrivalSpeed="37.95" duration="44.15" routeLength="995.70" waitingTime="0.16" waitingCount="1" stopTime="0.00" timeLoss="-7.70" rerouteNo="0" devices="tripinfo_v78.c_3" vType="vtypeauto" speedFactor="2.71" vaporized=""/>
    <tripinfo id="v79.a_1" depart="237.01" departLane="a+_0" departPos="4.10" departPosLat="0.00" departSpeed="0.00" departDelay="0.00" arrival="285.42" arrivalLane="b-_0" arrivalPos="492.80" arrivalPosLat="0.00" arrivalSpeed="26.68" duration="48.41" routeLength="990.53" waitingTime="0.16" waitingCount="1" stopTime="0.00" timeLoss="-3.18" rerouteNo="0" devices="tripinfo_v79.a_1" vType="vtypeauto" speedFactor="1.91" vaporized=""/>
    <tripinfo id="v87.a_2" depart="261.01" departLane="a+_0" departPos="4.10" departPosLat="0.00" departSpeed="0.00" departDelay="0.00" arrival="305.17" arrivalLane="c-_0" arrivalPos="492.80" arrivalPosLat="0.00" arrivalSpeed="37.95" duration="44.16" routeLength="995.90" waitingTime="0.16" waitingCount="1" stopTime="0.00" timeLoss="-7.70" rerouteNo="0" devices="tripinfo_v87.a_2" vType="vtypeauto" speedFactor="2.71" vaporized=""/>
    <tripinfo id="v99.b_1" depart="297.01" departLane="b+_0" departPos="4.10" departPosLat="0.00" departSpeed="0.00" departDelay="0.00" arrival="340.90" arrivalLane="c-_0" arrivalPos="492.80" arrivalPosLat="0.00" arrivalSpeed="37.95" duration="43.89" routeLength="990.53" waitingTime="0.16" waitingCount="1" stopTime="0.00" timeLoss="-7.70" rerouteNo="0" devices="tripinfo_v99.b_1" vType="vtypeauto" speedFactor="2.71" vaporized=""/>
    <tripinfo id="v104.c_1" depart="312.01" departLane="c+_0" departPos="4.10" departPosLat="0.00" departSpeed="0.00" departDelay="0.00" arrival="355.90" arrivalLane="d-_0" arrivalPos="492.80" arrivalPosLat="0.00" arrivalSpeed="37.95" duration="43.89" routeLength="990.53" waitingTime="0.16" waitingCount="1" stopTime="0.00" timeLoss="-7.70" rerouteNo="0" devices="tripinfo_v104.c_1" vType="vtypeauto" speedFactor="2.71" vaporized=""/>
    <tripinfo id="v106.d_2" depart="318.01" departLane="d+_0" departPos="4.10" departPosLat="0.00" departSpeed="0.00" departDelay="0.00" arrival="364.03" arrivalLane="b-_0" arrivalPos="492.80" arrivalPosLat="0.00" arrivalSpeed="31.99" duration="46.02" routeLength="995.90" waitingTime="0.16" waitingCount="1" stopTime="0.00" timeLoss="-5.82" rerouteNo="0" devices="tripinfo_v106.d_2" vType="vtypeauto" speedFactor="2.29" vaporized=""/>
    <tripinfo id="v104.b_2" depart="312.01" departLane="b+_0" departPos="4.10" departPosLat="0.00" departSpeed="0.00" departDelay="0.00" arrival="366.84" arrivalLane="d-_0" arrivalPos="492.80" arrivalPosLat="0.00" arrivalSpeed="21.94" duration="54.83" routeLength="995.90" waitingTime="0.16" waitingCount="1" stopTime="0.00" timeLoss="0.27" rerouteNo="0" devices="tripinfo_v104.b_2" vType="vtypeauto" speedFactor="1.57" vaporized=""/>
    <tripinfo id="v109.a_2" depart="327.01" departLane="a+_0" departPos="4.10" departPosLat="0.00" departSpeed="0.00" departDelay="0.00" arrival="371.52" arrivalLane="c-_0" arrivalPos="492.80" arrivalPosLat="0.00" arrivalSpeed="36.59" duration="44.51" routeLength="995.90" waitingTime="0.16" waitingCount="1" stopTime="0.00" timeLoss="-7.34" rerouteNo="0" devices="tripinfo_v109.a_2" vType="vtypeauto" speedFactor="2.61" vaporized=""/>
    <tripinfo id="v112.d_2" depart="336.01" departLane="d+_0" departPos="4.10" departPosLat="0.00" departSpeed="0.00" departDelay="0.00" arrival="380.52" arrivalLane="b-_0" arrivalPos="492.80" arrivalPosLat="0.00" arrivalSpeed="36.59" duration="44.51" routeLength="995.90" waitingTime="0.16" waitingCount="1" stopTime="0.00" timeLoss="-7.34" rerouteNo="0" devices="tripinfo_v112.d_2" vType="vtypeauto" speedFactor="2.61" vaporized=""/>
    <tripinfo id="v123.d_3" depart="369.01" departLane="d+_0" departPos="4.10" departPosLat="0.00" departSpeed="0.00" departDelay="0.00" arrival="413.16" arrivalLane="c-_0" arrivalPos="492.80" arrivalPosLat="0.00" arrivalSpeed="37.95" duration="44.15" routeLength="995.69" waitingTime="0.16" waitingCount="1" stopTime="0.00" timeLoss="-7.70" rerouteNo="0" devices="tripinfo_v123.d_3" vType="vtypeauto" speedFactor="2.71" vaporized=""/>
    <tripinfo id="v132.b_2" depart="396.01" departLane="b+_0" departPos="4.10" departPosLat="0.00" departSpeed="0.00" departDelay="0.00" arrival="440.17" arrivalLane="d-_0" arrivalPos="492.80" arrivalPosLat="0.00" arrivalSpeed="37.95" duration="44.16" routeLength="995.90" waitingTime="0.16" waitingCount="1" stopTime="0.00" timeLoss="-7.70" rerouteNo="0" devices="tripinfo_v132.b_2" vType="vtypeauto" speedFactor="2.71" vaporized=""/>
    <tripinfo id="v133.c_2" depart="399.01" departLane="c+_0" departPos="4.10" departPosLat="0.00" departSpeed="0.00" departDelay="0.00" arrival="447.68" arrivalLane="a-_0" arrivalPos="492.80" arrivalPosLat="0.00" arrivalSpeed="26.68" duration="48.67" routeLength="995.90" waitingTime="0.16" waitingCount="1" stopTime="0.00" timeLoss="-3.17" rerouteNo="0" devices="tripinfo_v133.c_2" vType="vtypeauto" speedFactor="1.91" vaporized=""/>
    <tripinfo id="v135.c_2" depart="405.01" departLane="c+_0" departPos="4.10" departPosLat="0.00" departSpeed="0.00" departDelay="0.00" arrival="450.41" arrivalLane="a-_0" arrivalPos="492.80" arrivalPosLat="0.00" arrivalSpeed="36.67" duration="45.40" routeLength="995.90" waitingTime="0.16" waitingCount="1" stopTime="0.00" timeLoss="-6.44" rerouteNo="0" devices="tripinfo_v135.c_2" vType="vtypeauto" speedFactor="2.61" vaporized=""/>
    <tripinfo id="v141.b_2" depart="423.01" departLane="b+_0" departPos="4.10" departPosLat="0.00" departSpeed="0.00" departDelay="0.00" arrival="467.17" arrivalLane="d-_0" arrivalPos="492.80" arrivalPosLat="0.00" arrivalSpeed="37.95" duration="44.16" routeLength="995.90" waitingTime="0.16" waitingCount="1" stopTime="0.00" timeLoss="-7.70" rerouteNo="0" devices="tripinfo_v141.b_2" vType="vtypeauto" speedFactor="2.71" vaporized=""/>
    <tripinfo id="v144.b_3" depart="432.01" departLane="b+_0" departPos="4.10" departPosLat="0.00" departSpeed="0.00" departDelay="0.00" arrival="476.16" arrivalLane="a-_0" arrivalPos="492.80" arrivalPosLat="0.00" arrivalSpeed="37.95" duration="44.15" routeLength="995.69" waitingTime="0.16" waitingCount="1" stopTime="0.00" timeLoss="-7.70" rerouteNo="0" devices="tripinfo_v144.b_3" vType="vtypeauto" speedFactor="2.71" vaporized=""/>
    <tripinfo id="v151.c_3" depart="453.01" departLane="c+_0" departPos="4.10" departPosLat="0.00" departSpeed="0.00" departDelay="0.00" arrival="497.16" arrivalLane="b-_0" arrivalPos="492.80" arrivalPosLat="0.00" arrivalSpeed="37.95" duration="44.15" routeLength="995.70" waitingTime="0.16" waitingCount="1" stopTime="0.00" timeLoss="-7.70" rerouteNo="0" devices="tripinfo_v151.c_3" vType="vtypeauto" speedFactor="2.71" vaporized=""/>
    <tripinfo id="v155.c_2" depart="465.01" departLane="c+_0" departPos="4.10" departPosLat="0.00" departSpeed="0.00" departDelay="0.00" arrival="509.17" arrivalLane="a-_0" arrivalPos="492.80" arrivalPosLat="0.00" arrivalSpeed="37.95" duration="44.16" routeLength="995.90" waitingTime="0.16" waitingCount="1" stopTime="0.00" timeLoss="-7.70" rerouteNo="0" devices="tripinfo_v155.c_2" vType="vtypeauto" speedFactor="2.71" vaporized=""/>
    <tripinfo id="v156.d_1" depart="468.01" departLane="d+_0" departPos="4.10" departPosLat="0.00" departSpeed="0.00" departDelay="0.00" arrival="516.42" arrivalLane="a-_0" arrivalPos="492.80" arrivalPosLat="0.00" arrivalSpeed="26.68" duration="48.41" routeLength="990.53" waitingTime="0.16" waitingCount="1" stopTime="0.00" timeLoss="-3.18" rerouteNo="0" devices="tripinfo_v156.d_1" vType="vtypeauto" speedFactor="1.91" vaporized=""/>
    <tripinfo id="v158.c_1" depart="474.01" departLane="c+_0" departPos="4.10" departPosLat="0.00" departSpeed="0.00" departDelay="0.00" arrival="519.76" arrivalLane="d-_0" arrivalPos="492.80" arrivalPosLat="0.00" arrivalSpeed="31.99" duration="45.75" routeLength="990.53" waitingTime="0.16" waitingCount="1" stopTime="0.00" timeLoss="-5.83" rerouteNo="0" devices="tripinfo_v158.c_1" vType="vtypeauto" speedFactor="2.29" vaporized=""/>
    <tripinfo id="v165.a_1" depart="495.01" departLane="a+_0" departPos="4.10" departPosLat="0.00" departSpeed="0.00" departDelay="0.00" arrival="538.90" arrivalLane="b-_0" arrivalPos="492.80" arrivalPosLat="0.00" arrivalSpeed="37.95" duration="43.89" routeLength="990.53" waitingTime="0.16" waitingCount="1" stopTime="0.00" timeLoss="-7.70" rerouteNo="0" devices="tripinfo_v165.a_1" vType="vtypeauto" speedFactor="2.71" vaporized=""/>
    <tripinfo id="v170.d_2" depart="510.01" departLane="d+_0" departPos="4.10" departPosLat="0.00" departSpeed="0.00" departDelay="0.00" arrival="554.17" arrivalLane="b-_0" arrivalPos="492.80" arrivalPosLat="0.00" arrivalSpeed="37.95" duration="44.16" routeLength="995.90" waitingTime="0.16" waitingCount="1" stopTime="0.00" timeLoss="-7.70" rerouteNo="0" devices="tripinfo_v170.d_2" vType="vtypeauto" speedFactor="2.71" vaporized=""/>
    <tripinfo id="v175.c_1" depart="525.01" departLane="c+_0" departPos="4.10" departPosLat="0.00" departSpeed="0.00" departDelay="0.00" arrival="568.90" arrivalLane="d-_0" arrivalPos="492.80" arrivalPosLat="0.00" arrivalSpeed="37.95" duration="43.89" routeLength="990.53" waitingTime="0.16" waitingCount="1" stopTime="0.00" timeLoss="-7.70" rerouteNo="0" devices="tripinfo_v175.c_1" vType="vtypeauto" speedFactor="2.71" vaporized=""/>
    <tripinfo id="v176.c_2" depart="528.01" departLane="c+_0" departPos="4.10" departPosLat="0.00" departSpeed="0.00" departDelay="0.00" arrival="572.18" arrivalLane="a-_0" arrivalPos="492.80" arrivalPosLat="0.00" arrivalSpeed="37.95" duration="44.17" routeLength="995.90" waitingTime="0.16" waitingCount="1" stopTime="0.00" timeLoss="-7.68" rerouteNo="0" devices="tripinfo_v176.c_2" vType="vtypeauto" speedFactor="2.71" vaporized=""/>
    <tripinfo id="v180.a_3" depart="540.01" departLane="a+_0" departPos="4.10" departPosLat="0.00" departSpeed="0.00" departDelay="0.00" arrival="584.16" arrivalLane="d-_0" arrivalPos="492.80" arrivalPosLat="0.00" arrivalSpeed="37.95" duration="44.15" routeLength="995.70" waitingTime="0.16" waitingCount="1" stopTime="0.00" timeLoss="-7.70" rerouteNo="0" devices="tripinfo_v180.a_3" vType="vtypeauto" speedFactor="2.71" vaporized=""/>
    <tripinfo id="v184.a_3" depart="552.01" departLane="a+_0" departPos="4.10" departPosLat="0.00" departSpeed="0.00" departDelay="0.00" arrival="596.16" arrivalLane="d-_0" arrivalPos="492.80" arrivalPosLat="0.00" arrivalSpeed="37.95" duration="44.15" routeLength="995.70" waitingTime="0.16" waitingCount="1" stopTime="0.00" timeLoss="-7.70" rerouteNo="0" devices="tripinfo_v184.a_3" vType="vtypeauto" speedFactor="2.71" vaporized=""/>
    <tripinfo id="v185.c_3" depart="555.01" departLane="c+_0" departPos="4.10" departPosLat="0.00" departSpeed="0.00" departDelay="0.00" arrival="599.16" arrivalLane="b-_0" arrivalPos="492.80" arrivalPosLat="0.00" arrivalSpeed="37.95" duration="44.15" routeLength="995.70" waitingTime="0.16" waitingCount="1" stopTime="0.00" timeLoss="-7.70" rerouteNo="0" devices="tripinfo_v185.c_3" vType="vtypeauto" speedFactor="2.71" vaporized=""/>
    <tripinfo id="v187.a_1" depart="561.01" departLane="a+_0" departPos="4.10" departPosLat="0.00" departSpeed="0.00" departDelay="0.00" arrival="606.76" arrivalLane="b-_0" arrivalPos="492.80" arrivalPosLat="0.00" arrivalSpeed="31.99" duration="45.75" routeLength="990.53" waitingTime="0.16" waitingCount="1" stopTime="0.00" timeLoss="-5.83" rerouteNo="0" devices="tripinfo_v187.a_1" vType="vtypeauto" speedFactor="2.29" vaporized=""/>
    <tripinfo id="v194.b_2" depart="582.01" departLane="b+_0" departPos="4.10" departPosLat="0.00" departSpeed="0.00" departDelay="0.00" arrival="626.17" arrivalLane="d-_0" arrivalPos="492.80" arrivalPosLat="0.00" arrivalSpeed="37.95" duration="44.16" routeLength="995.90" waitingTime="0.16" waitingCount="1" stopTime="0.00" timeLoss="-7.70" rerouteNo="0" devices="tripinfo_v194.b_2" vType="vtypeauto" speedFactor="2.71" vaporized=""/>
    <tripinfo id="v194.a_1" depart="582.01" departLane="a+_0" departPos="4.10" departPosLat="0.00" departSpeed="0.00" departDelay="0.00" arrival="636.57" arrivalLane="b-_0" arrivalPos="492.80" arrivalPosLat="0.00" arrivalSpeed="21.94" duration="54.56" routeLength="990.53" waitingTime="0.16" waitingCount="1" stopTime="0.00" timeLoss="0.26" rerouteNo="0" devices="tripinfo_v194.a_1" vType="vtypeauto" speedFactor="1.57" vaporized=""/>
    <tripinfo id="v199.a_2" depart="597.01" departLane="a+_0" departPos="4.10" departPosLat="0.00" departSpeed="0.00" departDelay="0.00" arrival="641.17" arrivalLane="c-_0" arrivalPos="492.80" arrivalPosLat="0.00" arrivalSpeed="37.95" duration="44.16" routeLength="995.90" waitingTime="0.16" waitingCount="1" stopTime="0.00" timeLoss="-7.70" rerouteNo="0" devices="tripinfo_v199.a_2" vType="vtypeauto" speedFactor="2.71" vaporized=""/>
    <tripinfo id="v205.a_2" depart="615.01" departLane="a+_0" departPos="4.10" departPosLat="0.00" departSpeed="0.00" departDelay="0.00" arrival="659.17" arrivalLane="c-_0" arrivalPos="492.80" arrivalPosLat="0.00" arrivalSpeed="37.95" duration="44.16" routeLength="995.90" waitingTime="0.16" waitingCount="1" stopTime="0.00" timeLoss="-7.70" rerouteNo="0" devices="tripinfo_v205.a_2" vType="vtypeauto" speedFactor="2.71" vaporized=""/>
    <tripinfo id="v208.d_3" depart="624.01" departLane="d+_0" departPos="4.10" departPosLat="0.00" departSpeed="0.00" departDelay="0.00" arrival="668.51" arrivalLane="c-_0" arrivalPos="492.80" arrivalPosLat="0.00" arrivalSpeed="36.59" duration="44.50" routeLength="995.69" waitingTime="0.16" waitingCount="1" stopTime="0.00" timeLoss="-7.34" rerouteNo="0" devices="tripinfo_v208.d_3" vType="vtypeauto" speedFactor="2.61" vaporized=""/>
    <tripinfo id="v220.b_2" depart="660.01" departLane="b+_0" departPos="4.10" departPosLat="0.00" departSpeed="0.00" departDelay="0.00" arrival="704.17" arrivalLane="d-_0" arrivalPos="492.80" arrivalPosLat="0.00" arrivalSpeed="37.95" duration="44.16" routeLength="995.90" waitingTime="0.16" waitingCount="1" stopTime="0.00" timeLoss="-7.70" rerouteNo="0" devices="tripinfo_v220.b_2" vType="vtypeauto" speedFactor="2.71" vaporized=""/>
    <tripinfo id="v225.a_3" depart="675.01" departLane="a+_0" departPos="4.10" departPosLat="0.00" departSpeed="0.00" departDelay="0.00" arrival="719.16" arrivalLane="d-_0" arrivalPos="492.80" arrivalPosLat="0.00" arrivalSpeed="37.95" duration="44.15" routeLength="995.70" waitingTime="0.16" waitingCount="1" stopTime="0.00" timeLoss="-7.70" rerouteNo="0" devices="tripinfo_v225.a_3" vType="vtypeauto" speedFactor="2.71" vaporized=""/>
    <tripinfo id="v225.c_3" depart="675.01" departLane="c+_0" departPos="4.10" departPosLat="0.00" departSpeed="0.00" departDelay="0.00" arrival="719.16" arrivalLane="b-_0" arrivalPos="492.80" arrivalPosLat="0.00" arrivalSpeed="37.95" duration="44.15" routeLength="995.70" waitingTime="0.16" waitingCount="1" stopTime="0.00" timeLoss="-7.70" rerouteNo="0" devices="tripinfo_v225.c_3" vType="vtypeauto" speedFactor="2.71" vaporized=""/>
    <tripinfo id="v231.d_1" depart="693.01" departLane="d+_0" departPos="4.10" departPosLat="0.00" departSpeed="0.00" departDelay="0.00" arrival="736.90" arrivalLane="a-_0" arrivalPos="492.80" arrivalPosLat="0.00" arrivalSpeed="37.95" duration="43.89" routeLength="990.53" waitingTime="0.16" waitingCount="1" stopTime="0.00" timeLoss="-7.70" rerouteNo="0" devices="tripinfo_v231.d_1" vType="vtypeauto" speedFactor="2.71" vaporized=""/>
    <tripinfo id="v243.c_3" depart="729.01" departLane="c+_0" departPos="4.10" departPosLat="0.00" departSpeed="0.00" departDelay="0.00" arrival="773.16" arrivalLane="b-_0" arrivalPos="492.80" arrivalPosLat="0.00" arrivalSpeed="37.95" duration="44.15" routeLength="995.70" waitingTime="0.16" waitingCount="1" stopTime="0.00" timeLoss="-7.70" rerouteNo="0" devices="tripinfo_v243.c_3" vType="vtypeauto" speedFactor="2.71" vaporized=""/>
    <tripinfo id="v264.c_1" depart="792.01" departLane="c+_0" departPos="4.10" departPosLat="0.00" departSpeed="0.00" departDelay="0.00" arrival="835.90" arrivalLane="d-_0" arrivalPos="492.80" arrivalPosLat="0.00" arrivalSpeed="37.95" duration="43.89" routeLength="990.53" waitingTime="0.16" waitingCount="1" stopTime="0.00" timeLoss="-7.70" rerouteNo="0" devices="tripinfo_v264.c_1" vType="vtypeauto" speedFactor="2.71" vaporized=""/>
    <tripinfo id="v279.c_3" depart="837.01" departLane="c+_0" departPos="4.10" departPosLat="0.00" departSpeed="0.00" departDelay="0.00" arrival="881.16" arrivalLane="b-_0" arrivalPos="492.80" arrivalPosLat="0.00" arrivalSpeed="37.95" duration="44.15" routeLength="995.70" waitingTime="0.16" waitingCount="1" stopTime="0.00" timeLoss="-7.70" rerouteNo="0" devices="tripinfo_v279.c_3" vType="vtypeauto" speedFactor="2.71" vaporized=""/>
    <tripinfo id="v280.a_3" depart="840.01" departLane="a+_0" departPos="4.10" departPosLat="0.00" departSpeed="0.00" departDelay="0.00" arrival="884.16" arrivalLane="d-_0" arrivalPos="492.80" arrivalPosLat="0.00" arrivalSpeed="37.95" duration="44.15" routeLength="995.70" waitingTime="0.16" waitingCount="1" stopTime="0.00" timeLoss="-7.70" rerouteNo="0" devices="tripinfo_v280.a_3" vType="vtypeauto" speedFactor="2.71" vaporized=""/>
    <tripinfo id="v283.d_1" depart="849.01" departLane="d+_0" departPos="4.10" departPosLat="0.00" departSpeed="0.00" departDelay="0.00" arrival="892.90" arrivalLane="a-_0" arrivalPos="492.80" arrivalPosLat="0.00" arrivalSpeed="37.95" duration="43.89" routeLength="990.53" waitingTime="0.16" waitingCount="1" stopTime="0.00" timeLoss="-7.70" rerouteNo="0" devices="tripinfo_v283.d_1" vType="vtypeauto" speedFactor="2.71" vaporized=""/>
    <tripinfo id="v285.a_2" depart="855.01" departLane="a+_0" departPos="4.10" departPosLat="0.00" departSpeed="0.00" departDelay="0.00" arrival="901.03" arrivalLane="c-_0" arrivalPos="492.80" arrivalPosLat="0.00" arrivalSpeed="31.99" duration="46.02" routeLength="995.90" waitingTime="0.16" waitingCount="1" stopTime="0.00" timeLoss="-5.82" rerouteNo="0" devices="tripinfo_v285.a_2" vType="vtypeauto" speedFactor="2.29" vaporized=""/>
    <tripinfo id="v289.b_1" depart="867.01" departLane="b+_0" departPos="4.10" departPosLat="0.00" departSpeed="0.00" departDelay="0.00" arrival="910.90" arrivalLane="c-_0" arrivalPos="492.80" arrivalPosLat="0.00" arrivalSpeed="37.95" duration="43.89" routeLength="990.53" waitingTime="0.16" waitingCount="1" stopTime="0.00" timeLoss="-7.70" rerouteNo="0" devices="tripinfo_v289.b_1" vType="vtypeauto" speedFactor="2.71" vaporized=""/>
    <tripinfo id="v292.b_3" depart="876.01" departLane="b+_0" departPos="4.10" departPosLat="0.00" departSpeed="0.00" departDelay="0.00" arrival="920.16" arrivalLane="a-_0" arrivalPos="492.80" arrivalPosLat="0.00" arrivalSpeed="37.95" duration="44.15" routeLength="995.69" waitingTime="0.16" waitingCount="1" stopTime="0.00" timeLoss="-7.70" rerouteNo="0" devices="tripinfo_v292.b_3" vType="vtypeauto" speedFactor="2.71" vaporized=""/>
    <tripinfo id="v302.b_2" depart="906.01" departLane="b+_0" departPos="4.10" departPosLat="0.00" departSpeed="0.00" departDelay="0.00" arrival="950.17" arrivalLane="d-_0" arrivalPos="492.80" arrivalPosLat="0.00" arrivalSpeed="37.95" duration="44.16" routeLength="995.90" waitingTime="0.16" waitingCount="1" stopTime="0.00" timeLoss="-7.70" rerouteNo="0" devices="tripinfo_v302.b_2" vType="vtypeauto" speedFactor="2.71" vaporized=""/>
    <tripinfo id="v314.d_3" depart="942.01" departLane="d+_0" departPos="4.10" departPosLat="0.00" departSpeed="0.00" departDelay="0.00" arrival="986.16" arrivalLane="c-_0" arrivalPos="492.80" arrivalPosLat="0.00" arrivalSpeed="37.95" duration="44.15" routeLength="995.69" waitingTime="0.16" waitingCount="1" stopTime="0.00" timeLoss="-7.70" rerouteNo="0" devices="tripinfo_v314.d_3" vType="vtypeauto" speedFactor="2.71" vaporized=""/>
    <tripinfo id="v322.a_2" depart="966.01" departLane="a+_0" departPos="4.10" departPosLat="0.00" departSpeed="0.00" departDelay="0.00" arrival="1010.17" arrivalLane="c-_0" arrivalPos="492.80" arrivalPosLat="0.00" arrivalSpeed="37.95" duration="44.16" routeLength="995.90" waitingTime="0.16" waitingCount="1" stopTime="0.00" timeLoss="-7.70" rerouteNo="0" devices="tripinfo_v322.a_2" vType="vtypeauto" speedFactor="2.71" vaporized=""/>
    <tripinfo id="v323.b_2" depart="969.01" departLane="b+_0" departPos="4.10" departPosLat="0.00" departSpeed="0.00" departDelay="0.00" arrival="1017.68" arrivalLane="d-_0" arrivalPos="492.80" arrivalPosLat="0.00" arrivalSpeed="26.68" duration="48.67" routeLength="995.90" waitingTime="0.16" waitingCount="1" stopTime="0.00" timeLoss="-3.17" rerouteNo="0" devices="tripinfo_v323.b_2" vType="vtypeauto" speedFactor="1.91" vaporized=""/>
    <tripinfo id="v335.d_3" depart="1005.01" departLane="d+_0" departPos="4.10" departPosLat="0.00" departSpeed="0.00" departDelay="0.00" arrival="1049.16" arrivalLane="c-_0" arrivalPos="492.80" arrivalPosLat="0.00" arrivalSpeed="37.95" duration="44.15" routeLength="995.69" waitingTime="0.16" waitingCount="1" stopTime="0.00" timeLoss="-7.70" rerouteNo="0" devices="tripinfo_v335.d_3" vType="vtypeauto" speedFactor="2.71" vaporized=""/>
    <tripinfo id="v348.b_2" depart="1044.01" departLane="b+_0" departPos="4.10" departPosLat="0.00" departSpeed="0.00" departDelay="0.00" arrival="1088.17" arrivalLane="d-_0" arrivalPos="492.80" arrivalPosLat="0.00" arrivalSpeed="37.95" duration="44.16" routeLength="995.90" waitingTime="0.16" waitingCount="1" stopTime="0.00" timeLoss="-7.70" rerouteNo="0" devices="tripinfo_v348.b_2" vType="vtypeauto" speedFactor="2.71" vaporized=""/>
    <tripinfo id="v348.a_3" depart="1044.01" departLane="a+_0" departPos="4.10" departPosLat="0.00" departSpeed="0.00" departDelay="0.00" arrival="1098.83" arrivalLane="d-_0" arrivalPos="492.80" arrivalPosLat="0.00" arrivalSpeed="21.94" duration="54.82" routeLength="995.70" waitingTime="0.16" waitingCount="1" stopTime="0.00" timeLoss="0.26" rerouteNo="0" devices="tripinfo_v348.a_3" vType="vtypeauto" speedFactor="1.57" vaporized=""/>
    <tripinfo id="v371.b_3" depart="1113.01" departLane="b+_0" departPos="4.10" departPosLat="0.00" departSpeed="0.00" departDelay="0.00" arrival="1157.16" arrivalLane="a-_0" arrivalPos="492.80" arrivalPosLat="0.00" arrivalSpeed="37.95" duration="44.15" routeLength="995.69" waitingTime="0.16" waitingCount="1" stopTime="0.00" timeLoss="-7.70" rerouteNo="0" devices="tripinfo_v371.b_3" vType="vtypeauto" speedFactor="2.71" vaporized=""/>
    <tripinfo id="v375.d_3" depart="1125.01" departLane="d+_0" departPos="4.10" departPosLat="0.00" departSpeed="0.00" departDelay="0.00" arrival="1169.16" arrivalLane="c-_0" arrivalPos="492.80" arrivalPosLat="0.00" arrivalSpeed="37.95" duration="44.15" routeLength="995.69" waitingTime="0.16" waitingCount="1" stopTime="0.00" timeLoss="-7.70" rerouteNo="0" devices="tripinfo_v375.d_3" vType="vtypeauto" speedFactor="2.71" vaporized=""/>
    <tripinfo id="v377.c_2" depart="1131.01" departLane="c+_0" departPos="4.10" departPosLat="0.00" departSpeed="0.00" departDelay="0.00" arrival="1175.17" arrivalLane="a-_0" arrivalPos="492.80" arrivalPosLat="0.00" arrivalSpeed="37.95" duration="44.16" routeLength="995.90" waitingTime="0.16" waitingCount="1" stopTime="0.00" timeLoss="-7.70" rerouteNo="0" devices="tripinfo_v377.c_2" vType="vtypeauto" speedFactor="2.71" vaporized=""/>
    <tripinfo id="v392.c_1" depart="1176.01" departLane="c+_0" departPos="4.10" departPosLat="0.00" departSpeed="0.00" departDelay="0.00" arrival="1219.90" arrivalLane="d-_0" arrivalPos="492.80" arrivalPosLat="0.00" arrivalSpeed="37.95" duration="43.89" routeLength="990.53" waitingTime="0.16" waitingCount="1" stopTime="0.00" timeLoss="-7.70" rerouteNo="0" devices="tripinfo_v392.c_1" vType="vtypeauto" speedFactor="2.71" vaporized=""/>
    <tripinfo id="v398.c_3" depart="1194.01" departLane="c+_0" departPos="4.10" departPosLat="0.00" departSpeed="0.00" departDelay="0.00" arrival="1238.16" arrivalLane="b-_0" arrivalPos="492.80" arrivalPosLat="0.00" arrivalSpeed="37.95" duration="44.15" routeLength="995.70" waitingTime="0.16" waitingCount="1" stopTime="0.00" timeLoss="-7.70" rerouteNo="0" devices="tripinfo_v398.c_3" vType="vtypeauto" speedFactor="2.71" vaporized=""/>
    <tripinfo id="v400.d_3" depart="1200.01" departLane="d+_0" departPos="4.10" departPosLat="0.00" departSpeed="0.00" departDelay="0.00" arrival="1244.16" arrivalLane="c-_0" arrivalPos="492.80" arrivalPosLat="0.00" arrivalSpeed="37.95" duration="44.15" routeLength="995.69" waitingTime="0.16" waitingCount="1" stopTime="0.00" timeLoss="-7.70" rerouteNo="0" devices="tripinfo_v400.d_3" vType="vtypeauto" speedFactor="2.71" vaporized=""/>
    <tripinfo id="v402.a_2" depart="1206.01" departLane="a+_0" departPos="4.10" departPosLat="0.00" departSpeed="0.00" departDelay="0.00" arrival="1252.03" arrivalLane="c-_0" arrivalPos="492.80" arrivalPosLat="0.00" arrivalSpeed="31.99" duration="46.02" routeLength="995.90" waitingTime="0.16" waitingCount="1" stopTime="0.00" timeLoss="-5.82" rerouteNo="0" devices="tripinfo_v402.a_2" vType="vtypeauto" speedFactor="2.29" vaporized=""/>
    <tripinfo id="v418.b_3" depart="1254.01" departLane="b+_0" departPos="4.10" departPosLat="0.00" departSpeed="0.00" departDelay="0.00" arrival="1298.16" arrivalLane="a-_0" arrivalPos="492.80" arrivalPosLat="0.00" arrivalSpeed="37.95" duration="44.15" routeLength="995.69" waitingTime="0.16" waitingCount="1" stopTime="0.00" timeLoss="-7.70" rerouteNo="0" devices="tripinfo_v418.b_3" vType="vtypeauto" speedFactor="2.71" vaporized=""/>
    <tripinfo id="v419.b_2" depart="1257.01" departLane="b+_0" departPos="4.10" departPosLat="0.00" departSpeed="0.00" departDelay="0.00" arrival="1301.18" arrivalLane="d-_0" arrivalPos="492.80" arrivalPosLat="0.00" arrivalSpeed="37.95" duration="44.17" routeLength="995.90" waitingTime="0.16" waitingCount="1" stopTime="0.00" timeLoss="-7.68" rerouteNo="0" devices="tripinfo_v419.b_2" vType="vtypeauto" speedFactor="2.71" vaporized=""/>
    <tripinfo id="v431.d_3" depart="1293.01" departLane="d+_0" departPos="4.10" departPosLat="0.00" departSpeed="0.00" departDelay="0.00" arrival="1337.16" arrivalLane="c-_0" arrivalPos="492.80" arrivalPosLat="0.00" arrivalSpeed="37.95" duration="44.15" routeLength="995.69" waitingTime="0.16" waitingCount="1" stopTime="0.00" timeLoss="-7.70" rerouteNo="0" devices="tripinfo_v431.d_3" vType="vtypeauto" speedFactor="2.71" vaporized=""/>
    <tripinfo id="v433.a_3" depart="1299.01" departLane="a+_0" departPos="4.10" departPosLat="0.00" departSpeed="0.00" departDelay="0.00" arrival="1343.16" arrivalLane="d-_0" arrivalPos="492.80" arrivalPosLat="0.00" arrivalSpeed="37.95" duration="44.15" routeLength="995.70" waitingTime="0.16" waitingCount="1" stopTime="0.00" timeLoss="-7.70" rerouteNo="0" devices="tripinfo_v433.a_3" vType="vtypeauto" speedFactor="2.71" vaporized=""/>
    <tripinfo id="v433.c_3" depart="1299.01" departLane="c+_0" departPos="4.10" departPosLat="0.00" departSpeed="0.00" departDelay="0.00" arrival="1343.16" arrivalLane="b-_0" arrivalPos="492.80" arrivalPosLat="0.00" arrivalSpeed="37.95" duration="44.15" routeLength="995.70" waitingTime="0.16" waitingCount="1" stopTime="0.00" timeLoss="-7.70" rerouteNo="0" devices="tripinfo_v433.c_3" vType="vtypeauto" speedFactor="2.71" vaporized=""/>
    <tripinfo id="v437.b_3" depart="1311.01" departLane="b+_0" departPos="4.10" departPosLat="0.00" departSpeed="0.00" departDelay="0.00" arrival="1355.16" arrivalLane="a-_0" arrivalPos="492.80" arrivalPosLat="0.00" arrivalSpeed="37.95" duration="44.15" routeLength="995.69" waitingTime="0.16" waitingCount="1" stopTime="0.00" timeLoss="-7.70" rerouteNo="0" devices="tripinfo_v437.b_3" vType="vtypeauto" speedFactor="2.71" vaporized=""/>
    <tripinfo id="v442.b_3" depart="1326.01" departLane="b+_0" departPos="4.10" departPosLat="0.00" departSpeed="0.00" departDelay="0.00" arrival="1370.16" arrivalLane="a-_0" arrivalPos="492.80" arrivalPosLat="0.00" arrivalSpeed="37.95" duration="44.15" routeLength="995.69" waitingTime="0.16" waitingCount="1" stopTime="0.00" timeLoss="-7.70" rerouteNo="0" devices="tripinfo_v442.b_3" vType="vtypeauto" speedFactor="2.71" vaporized=""/>
    <tripinfo id="v447.a_2" depart="1341.01" departLane="a+_0" departPos="4.10" departPosLat="0.00" departSpeed="0.00" departDelay="0.00" arrival="1385.17" arrivalLane="c-_0" arrivalPos="492.80" arrivalPosLat="0.00" arrivalSpeed="37.95" duration="44.16" routeLength="995.90" waitingTime="0.16" waitingCount="1" stopTime="0.00" timeLoss="-7.70" rerouteNo="0" devices="tripinfo_v447.a_2" vType="vtypeauto" speedFactor="2.71" vaporized=""/>
    <tripinfo id="v458.a_2" depart="1374.01" departLane="a+_0" departPos="4.10" departPosLat="0.00" departSpeed="0.00" departDelay="0.00" arrival="1418.17" arrivalLane="c-_0" arrivalPos="492.80" arrivalPosLat="0.00" arrivalSpeed="37.95" duration="44.16" routeLength="995.90" waitingTime="0.16" waitingCount="1" stopTime="0.00" timeLoss="-7.70" rerouteNo="0" devices="tripinfo_v458.a_2" vType="vtypeauto" speedFactor="2.71" vaporized=""/>
    <tripinfo id="v462.a_3" depart="1386.01" departLane="a+_0" departPos="4.10" departPosLat="0.00" departSpeed="0.00" departDelay="0.00" arrival="1430.16" arrivalLane="d-_0" arrivalPos="492.80" arrivalPosLat="0.00" arrivalSpeed="37.95" duration="44.15" routeLength="995.70" waitingTime="0.16" waitingCount="1" stopTime="0.00" timeLoss="-7.70" rerouteNo="0" devices="tripinfo_v462.a_3" vType="vtypeauto" speedFactor="2.71" vaporized=""/>
    <tripinfo id="v469.b_3" depart="1407.01" departLane="b+_0" departPos="4.10" departPosLat="0.00" departSpeed="0.00" departDelay="0.00" arrival="1451.16" arrivalLane="a-_0" arrivalPos="492.80" arrivalPosLat="0.00" arrivalSpeed="37.95" duration="44.15" routeLength="995.69" waitingTime="0.16" waitingCount="1" stopTime="0.00" timeLoss="-7.70" rerouteNo="0" devices="tripinfo_v469.b_3" vType="vtypeauto" speedFactor="2.71" vaporized=""/>
    <tripinfo id="v474.b_2" depart="1422.01" departLane="b+_0" departPos="4.10" departPosLat="0.00" departSpeed="0.00" departDelay="0.00" arrival="1466.17" arrivalLane="d-_0" arrivalPos="492.80" arrivalPosLat="0.00" arrivalSpeed="37.95" duration="44.16" routeLength="995.90" waitingTime="0.16" waitingCount="1" stopTime="0.00" timeLoss="-7.70" rerouteNo="0" devices="tripinfo_v474.b_2" vType="vtypeauto" speedFactor="2.71" vaporized=""/>
    <tripinfo id="v488.c_1" depart="1464.01" departLane="c+_0" departPos="4.10" departPosLat="0.00" departSpeed="0.00" departDelay="0.00" arrival="1507.90" arrivalLane="d-_0" arrivalPos="492.80" arrivalPosLat="0.00" arrivalSpeed="37.95" duration="43.89" routeLength="990.53" waitingTime="0.16" waitingCount="1" stopTime="0.00" timeLoss="-7.70" rerouteNo="0" devices="tripinfo_v488.c_1" vType="vtypeauto" speedFactor="2.71" vaporized=""/>
    <tripinfo id="v489.b_1" depart="1467.01" departLane="b+_0" departPos="4.10" departPosLat="0.00" departSpeed="0.00" departDelay="0.00" arrival="1515.42" arrivalLane="c-_0" arrivalPos="492.80" arrivalPosLat="0.00" arrivalSpeed="26.68" duration="48.41" routeLength="990.53" waitingTime="0.16" waitingCount="1" stopTime="0.00" timeLoss="-3.18" rerouteNo="0" devices="tripinfo_v489.b_1" vType="vtypeauto" speedFactor="1.91" vaporized=""/>
    <tripinfo id="v507.d_1" depart="1521.01" departLane="d+_0" departPos="4.10" departPosLat="0.00" departSpeed="0.00" departDelay="0.00" arrival="1564.90" arrivalLane="a-_0" arrivalPos="492.80" arrivalPosLat="0.00" arrivalSpeed="37.95" duration="43.89" routeLength="990.53" waitingTime="0.16" waitingCount="1" stopTime="0.00" timeLoss="-7.70" rerouteNo="0" devices="tripinfo_v507.d_1" vType="vtypeauto" speedFactor="2.71" vaporized=""/>
    <tripinfo id="v510.a_3" depart="1530.01" departLane="a+_0" departPos="4.10" departPosLat="0.00" departSpeed="0.00" departDelay="0.00" arrival="1574.16" arrivalLane="d-_0" arrivalPos="492.80" arrivalPosLat="0.00" arrivalSpeed="37.95" duration="44.15" routeLength="995.70" waitingTime="0.16" waitingCount="1" stopTime="0.00" timeLoss="-7.70" rerouteNo="0" devices="tripinfo_v510.a_3" vType="vtypeauto" speedFactor="2.71" vaporized=""/>
    <tripinfo id="v513.b_3" depart="1539.01" departLane="b+_0" departPos="4.10" departPosLat="0.00" departSpeed="0.00" departDelay="0.00" arrival="1583.16" arrivalLane="a-_0" arrivalPos="492.80" arrivalPosLat="0.00" arrivalSpeed="37.95" duration="44.15" routeLength="995.69" waitingTime="0.16" waitingCount="1" stopTime="0.00" timeLoss="-7.70" rerouteNo="0" devices="tripinfo_v513.b_3" vType="vtypeauto" speedFactor="2.71" vaporized=""/>
    <tripinfo id="v515.d_1" depart="1545.01" departLane="d+_0" departPos="4.10" departPosLat="0.00" departSpeed="0.00" departDelay="0.00" arrival="1590.76" arrivalLane="a-_0" arrivalPos="492.80" arrivalPosLat="0.00" arrivalSpeed="31.99" duration="45.75" routeLength="990.53" waitingTime="0.16" waitingCount="1" stopTime="0.00" timeLoss="-5.83" rerouteNo="0" devices="tripinfo_v515.d_1" vType="vtypeauto" speedFactor="2.29" vaporized=""/>
    <tripinfo id="v531.b_3" depart="1593.01" departLane="b+_0" departPos="4.10" departPosLat="0.00" departSpeed="0.00" departDelay="0.00" arrival="1637.16" arrivalLane="a-_0" arrivalPos="492.80" arrivalPosLat="0.00" arrivalSpeed="37.95" duration="44.15" routeLength="995.69" waitingTime="0.16" waitingCount="1" stopTime="0.00" timeLoss="-7.70" rerouteNo="0" devices="tripinfo_v531.b_3" vType="vtypeauto" speedFactor="2.71" vaporized=""/>
    <tripinfo id="v535.b_2" depart="1605.01" departLane="b+_0" departPos="4.10" departPosLat="0.00" departSpeed="0.00" departDelay="0.00" arrival="1649.17" arrivalLane="d-_0" arrivalPos="492.80" arrivalPosLat="0.00" arrivalSpeed="37.95" duration="44.16" routeLength="995.90" waitingTime="0.16" waitingCount="1" stopTime="0.00" timeLoss="-7.70" rerouteNo="0" devices="tripinfo_v535.b_2" vType="vtypeauto" speedFactor="2.71" vaporized=""/>
    <tripinfo id="v544.c_3" depart="1632.01" departLane="c+_0" departPos="4.10" departPosLat="0.00" departSpeed="0.00" departDelay="0.00" arrival="1676.16" arrivalLane="b-_0" arrivalPos="492.80" arrivalPosLat="0.00" arrivalSpeed="37.95" duration="44.15" routeLength="995.70" waitingTime="0.16" waitingCount="1" stopTime="0.00" timeLoss="-7.70" rerouteNo="0" devices="tripinfo_v544.c_3" vType="vtypeauto" speedFactor="2.71" vaporized=""/>
    <tripinfo id="v546.c_3" depart="1638.01" departLane="c+_0" departPos="4.10" departPosLat="0.00" departSpeed="0.00" departDelay="0.00" arrival="1682.16" arrivalLane="b-_0" arrivalPos="492.80" arrivalPosLat="0.00" arrivalSpeed="37.95" duration="44.15" routeLength="995.70" waitingTime="0.16" waitingCount="1" stopTime="0.00" timeLoss="-7.70" rerouteNo="0" devices="tripinfo_v546.c_3" vType="vtypeauto" speedFactor="2.71" vaporized=""/>
    <tripinfo id="v548.b_1" depart="1644.01" departLane="b+_0" departPos="4.10" departPosLat="0.00" departSpeed="0.00" departDelay="0.00" arrival="1687.90" arrivalLane="c-_0" arrivalPos="492.80" arrivalPosLat="0.00" arrivalSpeed="37.95" duration="43.89" routeLength="990.53" waitingTime="0.16" waitingCount="1" stopTime="0.00" timeLoss="-7.70" rerouteNo="0" devices="tripinfo_v548.b_1" vType="vtypeauto" speedFactor="2.71" vaporized=""/>
    <tripinfo id="v574.d_3" depart="1722.01" departLane="d+_0" departPos="4.10" departPosLat="0.00" departSpeed="0.00" departDelay="0.00" arrival="1766.16" arrivalLane="c-_0" arrivalPos="492.80" arrivalPosLat="0.00" arrivalSpeed="37.95" duration="44.15" routeLength="995.69" waitingTime="0.16" waitingCount="1" stopTime="0.00" timeLoss="-7.70" rerouteNo="0" devices="tripinfo_v574.d_3" vType="vtypeauto" speedFactor="2.71" vaporized=""/>
    <tripinfo id="v579.b_3" depart="1737.01" departLane="b+_0" departPos="4.10" departPosLat="0.00" departSpeed="0.00" departDelay="0.00" arrival="1781.16" arrivalLane="a-_0" arrivalPos="492.80" arrivalPosLat="0.00" arrivalSpeed="37.95" duration="44.15" routeLength="995.69" waitingTime="0.16" waitingCount="1" stopTime="0.00" timeLoss="-7.70" rerouteNo="0" devices="tripinfo_v579.b_3" vType="vtypeauto" speedFactor="2.71" vaporized=""/>
    <tripinfo id="v596.a_2" depart="1788.01" departLane="a+_0" departPos="4.10" departPosLat="0.00" departSpeed="0.00" departDelay="0.00" arrival="1832.17" arrivalLane="c-_0" arrivalPos="492.80" arrivalPosLat="0.00" arrivalSpeed="37.95" duration="44.16" routeLength="995.90" waitingTime="0.16" waitingCount="1" stopTime="0.00" timeLoss="-7.70" rerouteNo="0" devices="tripinfo_v596.a_2" vType="vtypeauto" speedFactor="2.71" vaporized=""/>
    <tripinfo id="v597.a_3" depart="1791.01" departLane="a+_0" departPos="4.10" departPosLat="0.00" departSpeed="0.00" departDelay="0.00" arrival="1835.17" arrivalLane="d-_0" arrivalPos="492.80" arrivalPosLat="0.00" arrivalSpeed="37.95" duration="44.16" routeLength="995.70" waitingTime="0.16" waitingCount="1" stopTime="0.00" timeLoss="-7.68" rerouteNo="0" devices="tripinfo_v597.a_3" vType="vtypeauto" speedFactor="2.71" vaporized=""/>
    <tripinfo id="v599.a_3" depart="1797.01" departLane="a+_0" departPos="4.10" departPosLat="0.00" departSpeed="0.00" departDelay="0.00" arrival="1841.16" arrivalLane="d-_0" arrivalPos="492.80" arrivalPosLat="0.00" arrivalSpeed="37.95" duration="44.15" routeLength="995.70" waitingTime="0.16" waitingCount="1" stopTime="0.00" timeLoss="-7.70" rerouteNo="0" devices="tripinfo_v599.a_3" vType="vtypeauto" speedFactor="2.71" vaporized=""/>
    <tripinfo id="v602.a_3" depart="1806.01" departLane="a+_0" departPos="4.10" departPosLat="0.00" departSpeed="0.00" departDelay="0.00" arrival="1850.16" arrivalLane="d-_0" arrivalPos="492.80" arrivalPosLat="0.00" arrivalSpeed="37.95" duration="44.15" routeLength="995.70" waitingTime="0.16" waitingCount="1" stopTime="0.00" timeLoss="-7.70" rerouteNo="0" devices="tripinfo_v602.a_3" vType="vtypeauto" speedFactor="2.71" vaporized=""/>
    <tripinfo id="v603.c_2" depart="1809.01" departLane="c+_0" departPos="4.10" departPosLat="0.00" departSpeed="0.00" departDelay="0.00" arrival="1853.17" arrivalLane="a-_0" arrivalPos="492.80" arrivalPosLat="0.00" arrivalSpeed="37.95" duration="44.16" routeLength="995.90" waitingTime="0.16" waitingCount="1" stopTime="0.00" timeLoss="-7.70" rerouteNo="0" devices="tripinfo_v603.c_2" vType="vtypeauto" speedFactor="2.71" vaporized=""/>
    <tripinfo id="v610.d_1" depart="1830.01" departLane="d+_0" departPos="4.10" departPosLat="0.00" departSpeed="0.00" departDelay="0.00" arrival="1873.90" arrivalLane="a-_0" arrivalPos="492.80" arrivalPosLat="0.00" arrivalSpeed="37.95" duration="43.89" routeLength="990.53" waitingTime="0.16" waitingCount="1" stopTime="0.00" timeLoss="-7.70" rerouteNo="0" devices="tripinfo_v610.d_1" vType="vtypeauto" speedFactor="2.71" vaporized=""/>
    <tripinfo id="v615.a_2" depart="1845.01" departLane="a+_0" departPos="4.10" departPosLat="0.00" departSpeed="0.00" departDelay="0.00" arrival="1889.17" arrivalLane="c-_0" arrivalPos="492.80" arrivalPosLat="0.00" arrivalSpeed="37.95" duration="44.16" routeLength="995.90" waitingTime="0.16" waitingCount="1" stopTime="0.00" timeLoss="-7.70" rerouteNo="0" devices="tripinfo_v615.a_2" vType="vtypeauto" speedFactor="2.71" vaporized=""/>
    <tripinfo id="v622.b_2" depart="1866.01" departLane="b+_0" departPos="4.10" departPosLat="0.00" departSpeed="0.00" departDelay="0.00" arrival="1910.17" arrivalLane="d-_0" arrivalPos="492.80" arrivalPosLat="0.00" arrivalSpeed="37.95" duration="44.16" routeLength="995.90" waitingTime="0.16" waitingCount="1" stopTime="0.00" timeLoss="-7.70" rerouteNo="0" devices="tripinfo_v622.b_2" vType="vtypeauto" speedFactor="2.71" vaporized=""/>
    <tripinfo id="v624.b_3" depart="1872.01" departLane="b+_0" departPos="4.10" departPosLat="0.00" departSpeed="0.00" departDelay="0.00" arrival="1916.16" arrivalLane="a-_0" arrivalPos="492.80" arrivalPosLat="0.00" arrivalSpeed="37.95" duration="44.15" routeLength="995.69" waitingTime="0.16" waitingCount="1" stopTime="0.00" timeLoss="-7.70" rerouteNo="0" devices="tripinfo_v624.b_3" vType="vtypeauto" speedFactor="2.71" vaporized=""/>
    <tripinfo id="v627.d_2" depart="1881.01" departLane="d+_0" departPos="4.10" departPosLat="0.00" departSpeed="0.00" departDelay="0.00" arrival="1925.17" arrivalLane="b-_0" arrivalPos="492.80" arrivalPosLat="0.00" arrivalSpeed="37.95" duration="44.16" routeLength="995.90" waitingTime="0.16" waitingCount="1" stopTime="0.00" timeLoss="-7.70" rerouteNo="0" devices="tripinfo_v627.d_2" vType="vtypeauto" speedFactor="2.71" vaporized=""/>
    <tripinfo id="v628.a_1" depart="1884.01" departLane="a+_0" departPos="4.10" departPosLat="0.00" departSpeed="0.00" departDelay="0.00" arrival="1932.42" arrivalLane="b-_0" arrivalPos="492.80" arrivalPosLat="0.00" arrivalSpeed="26.68" duration="48.41" routeLength="990.53" waitingTime="0.16" waitingCount="1" stopTime="0.00" timeLoss="-3.18" rerouteNo="0" devices="tripinfo_v628.a_1" vType="vtypeauto" speedFactor="1.91" vaporized=""/>
    <tripinfo id="v629.b_3" depart="1889.17" departLane="b+_0" departPos="4.10" departPosLat="0.00" departSpeed="0.00" departDelay="2.16" arrival="1933.40" arrivalLane="a-_0" arrivalPos="492.80" arrivalPosLat="0.00" arrivalSpeed="37.95" duration="44.23" routeLength="995.69" waitingTime="0.16" waitingCount="1" stopTime="0.00" timeLoss="-7.62" rerouteNo="0" devices="tripinfo_v629.b_3" vType="vtypeauto" speedFactor="2.71" vaporized=""/>
    <tripinfo id="v629.b_2" depart="1887.01" departLane="b+_0" departPos="4.10" departPosLat="0.00" departSpeed="0.00" departDelay="0.00" arrival="1935.68" arrivalLane="d-_0" arrivalPos="492.80" arrivalPosLat="0.00" arrivalSpeed="26.68" duration="48.67" routeLength="995.90" waitingTime="0.16" waitingCount="1" stopTime="0.00" timeLoss="-3.17" rerouteNo="0" devices="tripinfo_v629.b_2" vType="vtypeauto" speedFactor="1.91" vaporized=""/>
    <tripinfo id="v633.d_2" depart="1899.01" departLane="d+_0" departPos="4.10" departPosLat="0.00" departSpeed="0.00" departDelay="0.00" arrival="1943.17" arrivalLane="b-_0" arrivalPos="492.80" arrivalPosLat="0.00" arrivalSpeed="37.95" duration="44.16" routeLength="995.90" waitingTime="0.16" waitingCount="1" stopTime="0.00" timeLoss="-7.70" rerouteNo="0" devices="tripinfo_v633.d_2" vType="vtypeauto" speedFactor="2.71" vaporized=""/>
    <tripinfo id="v654.b_2" depart="1962.01" departLane="b+_0" departPos="4.10" departPosLat="0.00" departSpeed="0.00" departDelay="0.00" arrival="2006.17" arrivalLane="d-_0" arrivalPos="492.80" arrivalPosLat="0.00" arrivalSpeed="37.95" duration="44.16" routeLength="995.90" waitingTime="0.16" waitingCount="1" stopTime="0.00" timeLoss="-7.70" rerouteNo="0" devices="tripinfo_v654.b_2" vType="vtypeauto" speedFactor="2.71" vaporized=""/>
    <tripinfo id="v663.d_3" depart="1989.01" departLane="d+_0" departPos="4.10" departPosLat="0.00" departSpeed="0.00" departDelay="0.00" arrival="2033.16" arrivalLane="c-_0" arrivalPos="492.80" arrivalPosLat="0.00" arrivalSpeed="37.95" duration="44.15" routeLength="995.69" waitingTime="0.16" waitingCount="1" stopTime="0.00" timeLoss="-7.70" rerouteNo="0" devices="tripinfo_v663.d_3" vType="vtypeauto" speedFactor="2.71" vaporized=""/>
    <tripinfo id="v665.a_1" depart="1995.01" departLane="a+_0" departPos="4.10" departPosLat="0.00" departSpeed="0.00" departDelay="0.00" arrival="2038.90" arrivalLane="b-_0" arrivalPos="492.80" arrivalPosLat="0.00" arrivalSpeed="37.95" duration="43.89" routeLength="990.53" waitingTime="0.16" waitingCount="1" stopTime="0.00" timeLoss="-7.70" rerouteNo="0" devices="tripinfo_v665.a_1" vType="vtypeauto" speedFactor="2.71" vaporized=""/>
    <tripinfo id="v665.b_3" depart="1995.01" departLane="b+_0" departPos="4.10" departPosLat="0.00" departSpeed="0.00" departDelay="0.00" arrival="2039.16" arrivalLane="a-_0" arrivalPos="492.80" arrivalPosLat="0.00" arrivalSpeed="37.95" duration="44.15" routeLength="995.69" waitingTime="0.16" waitingCount="1" stopTime="0.00" timeLoss="-7.70" rerouteNo="0" devices="tripinfo_v665.b_3" vType="vtypeauto" speedFactor="2.71" vaporized=""/>
    <tripinfo id="v668.d_1" depart="2004.01" departLane="d+_0" departPos="4.10" departPosLat="0.00" departSpeed="0.00" departDelay="0.00" arrival="2048.25" arrivalLane="a-_0" arrivalPos="492.80" arrivalPosLat="0.00" arrivalSpeed="36.59" duration="44.24" routeLength="990.53" waitingTime="0.16" waitingCount="1" stopTime="0.00" timeLoss="-7.34" rerouteNo="0" devices="tripinfo_v668.d_1" vType="vtypeauto" speedFactor="2.61" vaporized=""/>
    <tripinfo id="v671.b_3" depart="2013.01" departLane="b+_0" departPos="4.10" departPosLat="0.00" departSpeed="0.00" departDelay="0.00" arrival="2057.51" arrivalLane="a-_0" arrivalPos="492.80" arrivalPosLat="0.00" arrivalSpeed="36.59" duration="44.50" routeLength="995.69" waitingTime="0.16" waitingCount="1" stopTime="0.00" timeLoss="-7.34" rerouteNo="0" devices="tripinfo_v671.b_3" vType="vtypeauto" speedFactor="2.61" vaporized=""/>
    <tripinfo id="v672.c_3" depart="2016.01" departLane="c+_0" departPos="4.10" departPosLat="0.00" departSpeed="0.00" departDelay="0.00" arrival="2060.16" arrivalLane="b-_0" arrivalPos="492.80" arrivalPosLat="0.00" arrivalSpeed="37.95" duration="44.15" routeLength="995.70" waitingTime="0.16" waitingCount="1" stopTime="0.00" timeLoss="-7.70" rerouteNo="0" devices="tripinfo_v672.c_3" vType="vtypeauto" speedFactor="2.71" vaporized=""/>
    <tripinfo id="v676.d_2" depart="2028.01" departLane="d+_0" departPos="4.10" departPosLat="0.00" departSpeed="0.00" departDelay="0.00" arrival="2072.18" arrivalLane="b-_0" arrivalPos="492.80" arrivalPosLat="0.00" arrivalSpeed="37.95" duration="44.17" routeLength="995.90" waitingTime="0.16" waitingCount="1" stopTime="0.00" timeLoss="-7.68" rerouteNo="0" devices="tripinfo_v676.d_2" vType="vtypeauto" speedFactor="2.71" vaporized=""/>
    <tripinfo id="v753.d_1" depart="2259.01" departLane="d+_0" departPos="4.10" departPosLat="0.00" departSpeed="0.00" departDelay="0.00" arrival="2302.90" arrivalLane="a-_0" arrivalPos="492.80" arrivalPosLat="0.00" arrivalSpeed="37.95" duration="43.89" routeLength="990.53" waitingTime="0.16" waitingCount="1" stopTime="0.00" timeLoss="-7.70" rerouteNo="0" devices="tripinfo_v753.d_1" vType="vtypeauto" speedFactor="2.71" vaporized=""/>
    <tripinfo id="v754.c_3" depart="2262.01" departLane="c+_0" departPos="4.10" departPosLat="0.00" departSpeed="0.00" departDelay="0.00" arrival="2306.16" arrivalLane="b-_0" arrivalPos="492.80" arrivalPosLat="0.00" arrivalSpeed="37.95" duration="44.15" routeLength="995.70" waitingTime="0.16" waitingCount="1" stopTime="0.00" timeLoss="-7.70" rerouteNo="0" devices="tripinfo_v754.c_3" vType="vtypeauto" speedFactor="2.71" vaporized=""/>
    <tripinfo id="v768.a_3" depart="2304.01" departLane="a+_0" departPos="4.10" departPosLat="0.00" departSpeed="0.00" departDelay="0.00" arrival="2348.16" arrivalLane="d-_0" arrivalPos="492.80" arrivalPosLat="0.00" arrivalSpeed="37.95" duration="44.15" routeLength="995.70" waitingTime="0.16" waitingCount="1" stopTime="0.00" timeLoss="-7.70" rerouteNo="0" devices="tripinfo_v768.a_3" vType="vtypeauto" speedFactor="2.71" vaporized=""/>
    <tripinfo id="v786.b_2" depart="2358.01" departLane="b+_0" departPos="4.10" departPosLat="0.00" departSpeed="0.00" departDelay="0.00" arrival="2402.17" arrivalLane="d-_0" arrivalPos="492.80" arrivalPosLat="0.00" arrivalSpeed="37.95" duration="44.16" routeLength="995.90" waitingTime="0.16" waitingCount="1" stopTime="0.00" timeLoss="-7.70" rerouteNo="0" devices="tripinfo_v786.b_2" vType="vtypeauto" speedFactor="2.71" vaporized=""/>
    <tripinfo id="v786.a_1" depart="2358.01" departLane="a+_0" departPos="4.10" departPosLat="0.00" departSpeed="0.00" departDelay="0.00" arrival="2412.57" arrivalLane="b-_0" arrivalPos="492.80" arrivalPosLat="0.00" arrivalSpeed="21.94" duration="54.56" routeLength="990.53" waitingTime="0.16" waitingCount="1" stopTime="0.00" timeLoss="0.26" rerouteNo="0" devices="tripinfo_v786.a_1" vType="vtypeauto" speedFactor="1.57" vaporized=""/>
    <tripinfo id="v791.b_2" depart="2373.01" departLane="b+_0" departPos="4.10" departPosLat="0.00" departSpeed="0.00" departDelay="0.00" arrival="2417.17" arrivalLane="d-_0" arrivalPos="492.80" arrivalPosLat="0.00" arrivalSpeed="37.95" duration="44.16" routeLength="995.90" waitingTime="0.16" waitingCount="1" stopTime="0.00" timeLoss="-7.70" rerouteNo="0" devices="tripinfo_v791.b_2" vType="vtypeauto" speedFactor="2.71" vaporized=""/>
    <tripinfo id="v794.a_3" depart="2382.01" departLane="a+_0" departPos="4.10" departPosLat="0.00" departSpeed="0.00" departDelay="0.00" arrival="2426.51" arrivalLane="d-_0" arrivalPos="492.80" arrivalPosLat="0.00" arrivalSpeed="36.59" duration="44.50" routeLength="995.70" waitingTime="0.16" waitingCount="1" stopTime="0.00" timeLoss="-7.34" rerouteNo="0" devices="tripinfo_v794.a_3" vType="vtypeauto" speedFactor="2.61" vaporized=""/>
    <tripinfo id="v795.a_3" depart="2385.01" departLane="a+_0" departPos="4.10" departPosLat="0.00" departSpeed="0.00" departDelay="0.00" arrival="2429.17" arrivalLane="d-_0" arrivalPos="492.80" arrivalPosLat="0.00" arrivalSpeed="37.95" duration="44.16" routeLength="995.70" waitingTime="0.16" waitingCount="1" stopTime="0.00" timeLoss="-7.68" rerouteNo="0" devices="tripinfo_v795.a_3" vType="vtypeauto" speedFactor="2.71" vaporized=""/>
    <tripinfo id="v819.d_3" depart="2457.01" departLane="d+_0" departPos="4.10" departPosLat="0.00" departSpeed="0.00" departDelay="0.00" arrival="2501.16" arrivalLane="c-_0" arrivalPos="492.80" arrivalPosLat="0.00" arrivalSpeed="37.95" duration="44.15" routeLength="995.69" waitingTime="0.16" waitingCount="1" stopTime="0.00" timeLoss="-7.70" rerouteNo="0" devices="tripinfo_v819.d_3" vType="vtypeauto" speedFactor="2.71" vaporized=""/>
    <tripinfo id="v819.c_2" depart="2457.01" departLane="c+_0" departPos="4.10" departPosLat="0.00" departSpeed="0.00" departDelay="0.00" arrival="2501.19" arrivalLane="a-_0" arrivalPos="492.80" arrivalPosLat="0.00" arrivalSpeed="37.95" duration="44.18" routeLength="995.90" waitingTime="0.16" waitingCount="1" stopTime="0.00" timeLoss="-7.66" rerouteNo="0" devices="tripinfo_v819.c_2" vType="vtypeauto" speedFactor="2.71" vaporized=""/>
    <tripinfo id="v826.c_1" depart="2478.01" departLane="c+_0" departPos="4.10" departPosLat="0.00" departSpeed="0.00" departDelay="0.00" arrival="2521.90" arrivalLane="d-_0" arrivalPos="492.80" arrivalPosLat="0.00" arrivalSpeed="37.95" duration="43.89" routeLength="990.53" waitingTime="0.16" waitingCount="1" stopTime="0.00" timeLoss="-7.70" rerouteNo="0" devices="tripinfo_v826.c_1" vType="vtypeauto" speedFactor="2.71" vaporized=""/>
    <tripinfo id="v839.b_2" depart="2517.01" departLane="b+_0" departPos="4.10" departPosLat="0.00" departSpeed="0.00" departDelay="0.00" arrival="2561.17" arrivalLane="d-_0" arrivalPos="492.80" arrivalPosLat="0.00" arrivalSpeed="37.95" duration="44.16" routeLength="995.90" waitingTime="0.16" waitingCount="1" stopTime="0.00" timeLoss="-7.70" rerouteNo="0" devices="tripinfo_v839.b_2" vType="vtypeauto" speedFactor="2.71" vaporized=""/>
    <tripinfo id="v841.d_1" depart="2523.01" departLane="d+_0" departPos="4.10" departPosLat="0.00" departSpeed="0.00" departDelay="0.00" arrival="2568.76" arrivalLane="a-_0" arrivalPos="492.80" arrivalPosLat="0.00" arrivalSpeed="31.99" duration="45.75" routeLength="990.53" waitingTime="0.16" waitingCount="1" stopTime="0.00" timeLoss="-5.83" rerouteNo="0" devices="tripinfo_v841.d_1" vType="vtypeauto" speedFactor="2.29" vaporized=""/>
    <tripinfo id="v849.d_1" depart="2547.01" departLane="d+_0" departPos="4.10" departPosLat="0.00" departSpeed="0.00" departDelay="0.00" arrival="2590.90" arrivalLane="a-_0" arrivalPos="492.80" arrivalPosLat="0.00" arrivalSpeed="37.95" duration="43.89" routeLength="990.53" waitingTime="0.16" waitingCount="1" stopTime="0.00" timeLoss="-7.70" rerouteNo="0" devices="tripinfo_v849.d_1" vType="vtypeauto" speedFactor="2.71" vaporized=""/>
    <tripinfo id="v857.d_2" depart="2571.01" departLane="d+_0" departPos="4.10" departPosLat="0.00" departSpeed="0.00" departDelay="0.00" arrival="2615.17" arrivalLane="b-_0" arrivalPos="492.80" arrivalPosLat="0.00" arrivalSpeed="37.95" duration="44.16" routeLength="995.90" waitingTime="0.16" waitingCount="1" stopTime="0.00" timeLoss="-7.70" rerouteNo="0" devices="tripinfo_v857.d_2" vType="vtypeauto" speedFactor="2.71" vaporized=""/>
    <tripinfo id="v874.d_1" depart="2622.01" departLane="d+_0" departPos="4.10" departPosLat="0.00" departSpeed="0.00" departDelay="0.00" arrival="2665.90" arrivalLane="a-_0" arrivalPos="492.80" arrivalPosLat="0.00" arrivalSpeed="37.95" duration="43.89" routeLength="990.53" waitingTime="0.16" waitingCount="1" stopTime="0.00" timeLoss="-7.70" rerouteNo="0" devices="tripinfo_v874.d_1" vType="vtypeauto" speedFactor="2.71" vaporized=""/>
    <tripinfo id="v875.d_3" depart="2625.01" departLane="d+_0" departPos="4.10" departPosLat="0.00" departSpeed="0.00" departDelay="0.00" arrival="2669.17" arrivalLane="c-_0" arrivalPos="492.80" arrivalPosLat="0.00" arrivalSpeed="37.95" duration="44.16" routeLength="995.69" waitingTime="0.16" waitingCount="1" stopTime="0.00" timeLoss="-7.68" rerouteNo="0" devices="tripinfo_v875.d_3" vType="vtypeauto" speedFactor="2.71" vaporized=""/>
    <tripinfo id="v890.d_1" depart="2670.01" departLane="d+_0" departPos="4.10" departPosLat="0.00" departSpeed="0.00" departDelay="0.00" arrival="2713.90" arrivalLane="a-_0" arrivalPos="492.80" arrivalPosLat="0.00" arrivalSpeed="37.95" duration="43.89" routeLength="990.53" waitingTime="0.16" waitingCount="1" stopTime="0.00" timeLoss="-7.70" rerouteNo="0" devices="tripinfo_v890.d_1" vType="vtypeauto" speedFactor="2.71" vaporized=""/>
    <tripinfo id="v892.d_3" depart="2676.01" departLane="d+_0" departPos="4.10" departPosLat="0.00" departSpeed="0.00" departDelay="0.00" arrival="2720.16" arrivalLane="c-_0" arrivalPos="492.80" arrivalPosLat="0.00" arrivalSpeed="37.95" duration="44.15" routeLength="995.69" waitingTime="0.16" waitingCount="1" stopTime="0.00" timeLoss="-7.70" rerouteNo="0" devices="tripinfo_v892.d_3" vType="vtypeauto" speedFactor="2.71" vaporized=""/>
    <tripinfo id="v892.b_3" depart="2676.01" departLane="b+_0" departPos="4.10" departPosLat="0.00" departSpeed="0.00" departDelay="0.00" arrival="2722.02" arrivalLane="a-_0" arrivalPos="492.80" arrivalPosLat="0.00" arrivalSpeed="31.99" duration="46.01" routeLength="995.69" waitingTime="0.16" waitingCount="1" stopTime="0.00" timeLoss="-5.82" rerouteNo="0" devices="tripinfo_v892.b_3" vType="vtypeauto" speedFactor="2.29" vaporized=""/>
    <tripinfo id="v893.c_3" depart="2679.01" departLane="c+_0" departPos="4.10" departPosLat="0.00" departSpeed="0.00" departDelay="0.00" arrival="2723.16" arrivalLane="b-_0" arrivalPos="492.80" arrivalPosLat="0.00" arrivalSpeed="37.95" duration="44.15" routeLength="995.70" waitingTime="0.16" waitingCount="1" stopTime="0.00" timeLoss="-7.70" rerouteNo="0" devices="tripinfo_v893.c_3" vType="vtypeauto" speedFactor="2.71" vaporized=""/>
    <tripinfo id="v906.c_1" depart="2718.01" departLane="c+_0" departPos="4.10" departPosLat="0.00" departSpeed="0.00" departDelay="0.00" arrival="2761.90" arrivalLane="d-_0" arrivalPos="492.80" arrivalPosLat="0.00" arrivalSpeed="37.95" duration="43.89" routeLength="990.53" waitingTime="0.16" waitingCount="1" stopTime="0.00" timeLoss="-7.70" rerouteNo="0" devices="tripinfo_v906.c_1" vType="vtypeauto" speedFactor="2.71" vaporized=""/>
    <tripinfo id="v923.a_1" depart="2769.01" departLane="a+_0" departPos="4.10" departPosLat="0.00" departSpeed="0.00" departDelay="0.00" arrival="2812.90" arrivalLane="b-_0" arrivalPos="492.80" arrivalPosLat="0.00" arrivalSpeed="37.95" duration="43.89" routeLength="990.53" waitingTime="0.16" waitingCount="1" stopTime="0.00" timeLoss="-7.70" rerouteNo="0" devices="tripinfo_v923.a_1" vType="vtypeauto" speedFactor="2.71" vaporized=""/>
    <tripinfo id="v927.d_1" depart="2781.01" departLane="d+_0" departPos="4.10" departPosLat="0.00" departSpeed="0.00" departDelay="0.00" arrival="2824.90" arrivalLane="a-_0" arrivalPos="492.80" arrivalPosLat="0.00" arrivalSpeed="37.95" duration="43.89" routeLength="990.53" waitingTime="0.16" waitingCount="1" stopTime="0.00" timeLoss="-7.70" rerouteNo="0" devices="tripinfo_v927.d_1" vType="vtypeauto" speedFactor="2.71" vaporized=""/>
    <tripinfo id="v937.c_2" depart="2811.01" departLane="c+_0" departPos="4.10" departPosLat="0.00" departSpeed="0.00" departDelay="0.00" arrival="2855.17" arrivalLane="a-_0" arrivalPos="492.80" arrivalPosLat="0.00" arrivalSpeed="37.95" duration="44.16" routeLength="995.90" waitingTime="0.16" waitingCount="1" stopTime="0.00" timeLoss="-7.70" rerouteNo="0" devices="tripinfo_v937.c_2" vType="vtypeauto" speedFactor="2.71" vaporized=""/>
    <tripinfo id="v939.d_2" depart="2817.01" departLane="d+_0" departPos="4.10" departPosLat="0.00" departSpeed="0.00" departDelay="0.00" arrival="2863.03" arrivalLane="b-_0" arrivalPos="492.80" arrivalPosLat="0.00" arrivalSpeed="31.99" duration="46.02" routeLength="995.90" waitingTime="0.16" waitingCount="1" stopTime="0.00" timeLoss="-5.82" rerouteNo="0" devices="tripinfo_v939.d_2" vType="vtypeauto" speedFactor="2.29" vaporized=""/>
    <tripinfo id="v945.c_1" depart="2835.01" departLane="c+_0" departPos="4.10" departPosLat="0.00" departSpeed="0.00" departDelay="0.00" arrival="2878.90" arrivalLane="d-_0" arrivalPos="492.80" arrivalPosLat="0.00" arrivalSpeed="37.95" duration="43.89" routeLength="990.53" waitingTime="0.16" waitingCount="1" stopTime="0.00" timeLoss="-7.70" rerouteNo="0" devices="tripinfo_v945.c_1" vType="vtypeauto" speedFactor="2.71" vaporized=""/>
    <tripinfo id="v946.d_1" depart="2838.01" departLane="d+_0" departPos="4.10" departPosLat="0.00" departSpeed="0.00" departDelay="0.00" arrival="2886.42" arrivalLane="a-_0" arrivalPos="492.80" arrivalPosLat="0.00" arrivalSpeed="26.68" duration="48.41" routeLength="990.53" waitingTime="0.16" waitingCount="1" stopTime="0.00" timeLoss="-3.18" rerouteNo="0" devices="tripinfo_v946.d_1" vType="vtypeauto" speedFactor="1.91" vaporized=""/>
    <tripinfo id="v947.a_3" depart="2843.17" departLane="a+_0" departPos="4.10" departPosLat="0.00" departSpeed="0.00" departDelay="2.16" arrival="2888.09" arrivalLane="d-_0" arrivalPos="492.80" arrivalPosLat="0.00" arrivalSpeed="35.38" duration="44.92" routeLength="995.70" waitingTime="0.16" waitingCount="1" stopTime="0.00" timeLoss="-6.91" rerouteNo="0" devices="tripinfo_v947.a_3" vType="vtypeauto" speedFactor="2.53" vaporized=""/>
    <tripinfo id="v947.a_2" depart="2841.01" departLane="a+_0" departPos="4.10" departPosLat="0.00" departSpeed="0.00" departDelay="0.00" arrival="2889.68" arrivalLane="c-_0" arrivalPos="492.80" arrivalPosLat="0.00" arrivalSpeed="26.68" duration="48.67" routeLength="995.90" waitingTime="0.16" waitingCount="1" stopTime="0.00" timeLoss="-3.17" rerouteNo="0" devices="tripinfo_v947.a_2" vType="vtypeauto" speedFactor="1.91" vaporized=""/>
    <tripinfo id="v949.a_2" depart="2847.01" departLane="a+_0" departPos="4.10" departPosLat="0.00" departSpeed="0.00" departDelay="0.00" arrival="2892.41" arrivalLane="c-_0" arrivalPos="492.80" arrivalPosLat="0.00" arrivalSpeed="36.65" duration="45.40" routeLength="995.90" waitingTime="0.16" waitingCount="1" stopTime="0.00" timeLoss="-6.44" rerouteNo="0" devices="tripinfo_v949.a_2" vType="vtypeauto" speedFactor="2.61" vaporized=""/>
    <tripinfo id="v964.b_1" depart="2892.01" departLane="b+_0" departPos="4.10" departPosLat="0.00" departSpeed="0.00" departDelay="0.00" arrival="2935.90" arrivalLane="c-_0" arrivalPos="492.80" arrivalPosLat="0.00" arrivalSpeed="37.95" duration="43.89" routeLength="990.53" waitingTime="0.16" waitingCount="1" stopTime="0.00" timeLoss="-7.70" rerouteNo="0" devices="tripinfo_v964.b_1" vType="vtypeauto" speedFactor="2.71" vaporized=""/>
    <tripinfo id="v967.c_3" depart="2901.01" departLane="c+_0" departPos="4.10" departPosLat="0.00" departSpeed="0.00" departDelay="0.00" arrival="2945.16" arrivalLane="b-_0" arrivalPos="492.80" arrivalPosLat="0.00" arrivalSpeed="37.95" duration="44.15" routeLength="995.70" waitingTime="0.16" waitingCount="1" stopTime="0.00" timeLoss="-7.70" rerouteNo="0" devices="tripinfo_v967.c_3" vType="vtypeauto" speedFactor="2.71" vaporized=""/>
    <tripinfo id="v969.a_1" depart="2907.01" departLane="a+_0" departPos="4.10" departPosLat="0.00" departSpeed="0.00" departDelay="0.00" arrival="2952.76" arrivalLane="b-_0" arrivalPos="492.80" arrivalPosLat="0.00" arrivalSpeed="31.99" duration="45.75" routeLength="990.53" waitingTime="0.16" waitingCount="1" stopTime="0.00" timeLoss="-5.83" rerouteNo="0" devices="tripinfo_v969.a_1" vType="vtypeauto" speedFactor="2.29" vaporized=""/>
    <tripinfo id="v971.a_2" depart="2913.01" departLane="a+_0" departPos="4.10" departPosLat="0.00" departSpeed="0.00" departDelay="0.00" arrival="2957.17" arrivalLane="c-_0" arrivalPos="492.80" arrivalPosLat="0.00" arrivalSpeed="37.95" duration="44.16" routeLength="995.90" waitingTime="0.16" waitingCount="1" stopTime="0.00" timeLoss="-7.70" rerouteNo="0" devices="tripinfo_v971.a_2" vType="vtypeauto" speedFactor="2.71" vaporized=""/>
    <tripinfo id="v992.a_3" depart="2976.01" departLane="a+_0" departPos="4.10" departPosLat="0.00" departSpeed="0.00" departDelay="0.00" arrival="3020.16" arrivalLane="d-_0" arrivalPos="492.80" arrivalPosLat="0.00" arrivalSpeed="37.95" duration="44.15" routeLength="995.70" waitingTime="0.16" waitingCount="1" stopTime="0.00" timeLoss="-7.70" rerouteNo="0" devices="tripinfo_v992.a_3" vType="vtypeauto" speedFactor="2.71" vaporized=""/>
    <tripinfo id="v999.b_1" depart="2997.01" departLane="b+_0" departPos="4.10" departPosLat="0.00" departSpeed="0.00" departDelay="0.00" arrival="3040.90" arrivalLane="c-_0" arrivalPos="492.80" arrivalPosLat="0.00" arrivalSpeed="37.95" duration="43.89" routeLength="990.53" waitingTime="0.16" waitingCount="1" stopTime="0.00" timeLoss="-7.70" rerouteNo="0" devices="tripinfo_v999.b_1" vType="vtypeauto" speedFactor="2.71" vaporized=""/>
    <tripinfo id="v1001.d_2" depart="3003.01" departLane="d+_0" departPos="4.10" departPosLat="0.00" departSpeed="0.00" departDelay="0.00" arrival="3049.03" arrivalLane="b-_0" arrivalPos="492.80" arrivalPosLat="0.00" arrivalSpeed="31.99" duration="46.02" routeLength="995.90" waitingTime="0.16" waitingCount="1" stopTime="0.00" timeLoss="-5.82" rerouteNo="0" devices="tripinfo_v1001.d_2" vType="vtypeauto" speedFactor="2.29" vaporized=""/>
    <tripinfo id="v1006.d_2" depart="3018.01" departLane="d+_0" departPos="4.10" departPosLat="0.00" departSpeed="0.00" departDelay="0.00" arrival="3062.17" arrivalLane="b-_0" arrivalPos="492.80" arrivalPosLat="0.00" arrivalSpeed="37.95" duration="44.16" routeLength="995.90" waitingTime="0.16" waitingCount="1" stopTime="0.00" timeLoss="-7.70" rerouteNo="0" devices="tripinfo_v1006.d_2" vType="vtypeauto" speedFactor="2.71" vaporized=""/>
    <tripinfo id="v1010.a_1" depart="3030.01" departLane="a+_0" departPos="4.10" departPosLat="0.00" departSpeed="0.00" departDelay="0.00" arrival="3073.90" arrivalLane="b-_0" arrivalPos="492.80" arrivalPosLat="0.00" arrivalSpeed="37.95" duration="43.89" routeLength="990.53" waitingTime="0.16" waitingCount="1" stopTime="0.00" timeLoss="-7.70" rerouteNo="0" devices="tripinfo_v1010.a_1" vType="vtypeauto" speedFactor="2.71" vaporized=""/>
    <tripinfo id="v1012.b_1" depart="3036.01" departLane="b+_0" departPos="4.10" departPosLat="0.00" departSpeed="0.00" departDelay="0.00" arrival="3081.76" arrivalLane="c-_0" arrivalPos="492.80" arrivalPosLat="0.00" arrivalSpeed="31.99" duration="45.75" routeLength="990.53" waitingTime="0.16" waitingCount="1" stopTime="0.00" timeLoss="-5.83" rerouteNo="0" devices="tripinfo_v1012.b_1" vType="vtypeauto" speedFactor="2.29" vaporized=""/>
    <tripinfo id="v1024.a_2" depart="3072.01" departLane="a+_0" departPos="4.10" departPosLat="0.00" departSpeed="0.00" departDelay="0.00" arrival="3116.17" arrivalLane="c-_0" arrivalPos="492.80" arrivalPosLat="0.00" arrivalSpeed="37.95" duration="44.16" routeLength="995.90" waitingTime="0.16" waitingCount="1" stopTime="0.00" timeLoss="-7.70" rerouteNo="0" devices="tripinfo_v1024.a_2" vType="vtypeauto" speedFactor="2.71" vaporized=""/>
    <tripinfo id="v1031.b_1" depart="3093.01" departLane="b+_0" departPos="4.10" departPosLat="0.00" departSpeed="0.00" departDelay="0.00" arrival="3136.90" arrivalLane="c-_0" arrivalPos="492.80" arrivalPosLat="0.00" arrivalSpeed="37.95" duration="43.89" routeLength="990.53" waitingTime="0.16" waitingCount="1" stopTime="0.00" timeLoss="-7.70" rerouteNo="0" devices="tripinfo_v1031.b_1" vType="vtypeauto" speedFactor="2.71" vaporized=""/>
    <tripinfo id="v1031.d_2" depart="3093.01" departLane="d+_0" departPos="4.10" departPosLat="0.00" departSpeed="0.00" departDelay="0.00" arrival="3147.84" arrivalLane="b-_0" arrivalPos="492.80" arrivalPosLat="0.00" arrivalSpeed="21.94" duration="54.83" routeLength="995.90" waitingTime="0.16" waitingCount="1" stopTime="0.00" timeLoss="0.27" rerouteNo="0" devices="tripinfo_v1031.d_2" vType="vtypeauto" speedFactor="1.57" vaporized=""/>
    <tripinfo id="v1070.d_2" depart="3210.01" departLane="d+_0" departPos="4.10" departPosLat="0.00" departSpeed="0.00" departDelay="0.00" arrival="3254.17" arrivalLane="b-_0" arrivalPos="492.80" arrivalPosLat="0.00" arrivalSpeed="37.95" duration="44.16" routeLength="995.90" waitingTime="0.16" waitingCount="1" stopTime="0.00" timeLoss="-7.70" rerouteNo="0" devices="tripinfo_v1070.d_2" vType="vtypeauto" speedFactor="2.71" vaporized=""/>
    <tripinfo id="v1092.c_2" depart="3276.01" departLane="c+_0" departPos="4.10" departPosLat="0.00" departSpeed="0.00" departDelay="0.00" arrival="3320.17" arrivalLane="a-_0" arrivalPos="492.80" arrivalPosLat="0.00" arrivalSpeed="37.95" duration="44.16" routeLength="995.90" waitingTime="0.16" waitingCount="1" stopTime="0.00" timeLoss="-7.70" rerouteNo="0" devices="tripinfo_v1092.c_2" vType="vtypeauto" speedFactor="2.71" vaporized=""/>
    <tripinfo id="v1094.c_1" depart="3282.01" departLane="c+_0" departPos="4.10" departPosLat="0.00" departSpeed="0.00" departDelay="0.00" arrival="3325.90" arrivalLane="d-_0" arrivalPos="492.80" arrivalPosLat="0.00" arrivalSpeed="37.95" duration="43.89" routeLength="990.53" waitingTime="0.16" waitingCount="1" stopTime="0.00" timeLoss="-7.70" rerouteNo="0" devices="tripinfo_v1094.c_1" vType="vtypeauto" speedFactor="2.71" vaporized=""/>
    <tripinfo id="v1099.a_1" depart="3297.01" departLane="a+_0" departPos="4.10" departPosLat="0.00" departSpeed="0.00" departDelay="0.00" arrival="3340.90" arrivalLane="b-_0" arrivalPos="492.80" arrivalPosLat="0.00" arrivalSpeed="37.95" duration="43.89" routeLength="990.53" waitingTime="0.16" waitingCount="1" stopTime="0.00" timeLoss="-7.70" rerouteNo="0" devices="tripinfo_v1099.a_1" vType="vtypeauto" speedFactor="2.71" vaporized=""/>
    <tripinfo id="v1100.c_1" depart="3300.01" departLane="c+_0" departPos="4.10" departPosLat="0.00" departSpeed="0.00" departDelay="0.00" arrival="3343.90" arrivalLane="d-_0" arrivalPos="492.80" arrivalPosLat="0.00" arrivalSpeed="37.95" duration="43.89" routeLength="990.53" waitingTime="0.16" waitingCount="1" stopTime="0.00" timeLoss="-7.70" rerouteNo="0" devices="tripinfo_v1100.c_1" vType="vtypeauto" speedFactor="2.71" vaporized=""/>
    <tripinfo id="v1104.a_2" depart="3312.01" departLane="a+_0" departPos="4.10" departPosLat="0.00" departSpeed="0.00" departDelay="0.00" arrival="3356.17" arrivalLane="c-_0" arrivalPos="492.80" arrivalPosLat="0.00" arrivalSpeed="37.95" duration="44.16" routeLength="995.90" waitingTime="0.16" waitingCount="1" stopTime="0.00" timeLoss="-7.70" rerouteNo="0" devices="tripinfo_v1104.a_2" vType="vtypeauto" speedFactor="2.71" vaporized=""/>
    <tripinfo id="v1107.a_2" depart="3321.01" departLane="a+_0" departPos="4.10" departPosLat="0.00" departSpeed="0.00" departDelay="0.00" arrival="3365.17" arrivalLane="c-_0" arrivalPos="492.80" arrivalPosLat="0.00" arrivalSpeed="37.95" duration="44.16" routeLength="995.90" waitingTime="0.16" waitingCount="1" stopTime="0.00" timeLoss="-7.70" rerouteNo="0" devices="tripinfo_v1107.a_2" vType="vtypeauto" speedFactor="2.71" vaporized=""/>
    <tripinfo id="v1111.d_2" depart="3333.01" departLane="d+_0" departPos="4.10" departPosLat="0.00" departSpeed="0.00" departDelay="0.00" arrival="3377.17" arrivalLane="b-_0" arrivalPos="492.80" arrivalPosLat="0.00" arrivalSpeed="37.95" duration="44.16" routeLength="995.90" waitingTime="0.16" waitingCount="1" stopTime="0.00" timeLoss="-7.70" rerouteNo="0" devices="tripinfo_v1111.d_2" vType="vtypeauto" speedFactor="2.71" vaporized=""/>
    <tripinfo id="v1111.d_3" depart="3335.17" departLane="d+_0" departPos="4.10" departPosLat="0.00" departSpeed="0.00" departDelay="2.16" arrival="3379.40" arrivalLane="c-_0" arrivalPos="492.80" arrivalPosLat="0.00" arrivalSpeed="37.95" duration="44.23" routeLength="995.69" waitingTime="0.16" waitingCount="1" stopTime="0.00" timeLoss="-7.62" rerouteNo="0" devices="tripinfo_v1111.d_3" vType="vtypeauto" speedFactor="2.71" vaporized=""/>
    <tripinfo id="v1115.c_2" depart="3345.01" departLane="c+_0" departPos="4.10" departPosLat="0.00" departSpeed="0.00" departDelay="0.00" arrival="3389.17" arrivalLane="a-_0" arrivalPos="492.80" arrivalPosLat="0.00" arrivalSpeed="37.95" duration="44.16" routeLength="995.90" waitingTime="0.16" waitingCount="1" stopTime="0.00" timeLoss="-7.70" rerouteNo="0" devices="tripinfo_v1115.c_2" vType="vtypeauto" speedFactor="2.71" vaporized=""/>
    <tripinfo id="v1116.d_2" depart="3348.01" departLane="d+_0" departPos="4.10" departPosLat="0.00" departSpeed="0.00" departDelay="0.00" arrival="3396.68" arrivalLane="b-_0" arrivalPos="492.80" arrivalPosLat="0.00" arrivalSpeed="26.68" duration="48.67" routeLength="995.90" waitingTime="0.16" waitingCount="1" stopTime="0.00" timeLoss="-3.17" rerouteNo="0" devices="tripinfo_v1116.d_2" vType="vtypeauto" speedFactor="1.91" vaporized=""/>
    <tripinfo id="v1117.a_2" depart="3351.01" departLane="a+_0" departPos="4.10" departPosLat="0.00" departSpeed="0.00" departDelay="0.00" arrival="3399.68" arrivalLane="c-_0" arrivalPos="492.80" arrivalPosLat="0.00" arrivalSpeed="26.68" duration="48.67" routeLength="995.90" waitingTime="0.16" waitingCount="1" stopTime="0.00" timeLoss="-3.17" rerouteNo="0" devices="tripinfo_v1117.a_2" vType="vtypeauto" speedFactor="1.91" vaporized=""/>
    <tripinfo id="v1118.d_1" depart="3354.01" departLane="d+_0" departPos="4.10" departPosLat="0.00" departSpeed="0.00" departDelay="0.00" arrival="3402.42" arrivalLane="a-_0" arrivalPos="492.80" arrivalPosLat="0.00" arrivalSpeed="26.68" duration="48.41" routeLength="990.53" waitingTime="0.16" waitingCount="1" stopTime="0.00" timeLoss="-3.18" rerouteNo="0" devices="tripinfo_v1118.d_1" vType="vtypeauto" speedFactor="1.91" vaporized=""/>
    <tripinfo id="v1121.d_1" depart="3363.01" departLane="d+_0" departPos="4.10" departPosLat="0.00" departSpeed="0.00" departDelay="0.00" arrival="3406.90" arrivalLane="a-_0" arrivalPos="492.80" arrivalPosLat="0.00" arrivalSpeed="37.95" duration="43.89" routeLength="990.53" waitingTime="0.16" waitingCount="1" stopTime="0.00" timeLoss="-7.69" rerouteNo="0" devices="tripinfo_v1121.d_1" vType="vtypeauto" speedFactor="2.71" vaporized=""/>
    <tripinfo id="v1123.b_2" depart="3369.01" departLane="b+_0" departPos="4.10" departPosLat="0.00" departSpeed="0.00" departDelay="0.00" arrival="3415.03" arrivalLane="d-_0" arrivalPos="492.80" arrivalPosLat="0.00" arrivalSpeed="31.99" duration="46.02" routeLength="995.90" waitingTime="0.16" waitingCount="1" stopTime="0.00" timeLoss="-5.82" rerouteNo="0" devices="tripinfo_v1123.b_2" vType="vtypeauto" speedFactor="2.29" vaporized=""/>
    <tripinfo id="v1124.d_2" depart="3372.01" departLane="d+_0" departPos="4.10" departPosLat="0.00" departSpeed="0.00" departDelay="0.00" arrival="3416.17" arrivalLane="b-_0" arrivalPos="492.80" arrivalPosLat="0.00" arrivalSpeed="37.95" duration="44.16" routeLength="995.90" waitingTime="0.16" waitingCount="1" stopTime="0.00" timeLoss="-7.70" rerouteNo="0" devices="tripinfo_v1124.d_2" vType="vtypeauto" speedFactor="2.71" vaporized=""/>
    <tripinfo id="v1138.d_2" depart="3414.01" departLane="d+_0" departPos="4.10" departPosLat="0.00" departSpeed="0.00" departDelay="0.00" arrival="3458.17" arrivalLane="b-_0" arrivalPos="492.80" arrivalPosLat="0.00" arrivalSpeed="37.95" duration="44.16" routeLength="995.90" waitingTime="0.16" waitingCount="1" stopTime="0.00" timeLoss="-7.70" rerouteNo="0" devices="tripinfo_v1138.d_2" vType="vtypeauto" speedFactor="2.71" vaporized=""/>
    <tripinfo id="v1138.a_3" depart="3414.01" departLane="a+_0" departPos="4.10" departPosLat="0.00" departSpeed="0.00" departDelay="0.00" arrival="3458.21" arrivalLane="d-_0" arrivalPos="492.80" arrivalPosLat="0.00" arrivalSpeed="37.95" duration="44.20" routeLength="995.70" waitingTime="0.16" waitingCount="1" stopTime="0.00" timeLoss="-7.65" rerouteNo="0" devices="tripinfo_v1138.a_3" vType="vtypeauto" speedFactor="2.71" vaporized=""/>
    <tripinfo id="v1140.a_2" depart="3420.01" departLane="a+_0" departPos="4.10" departPosLat="0.00" departSpeed="0.00" departDelay="0.00" arrival="3466.03" arrivalLane="c-_0" arrivalPos="492.80" arrivalPosLat="0.00" arrivalSpeed="31.99" duration="46.02" routeLength="995.90" waitingTime="0.16" waitingCount="1" stopTime="0.00" timeLoss="-5.82" rerouteNo="0" devices="tripinfo_v1140.a_2" vType="vtypeauto" speedFactor="2.29" vaporized=""/>
    <tripinfo id="v1147.c_1" depart="3441.01" departLane="c+_0" departPos="4.10" departPosLat="0.00" departSpeed="0.00" departDelay="0.00" arrival="3484.90" arrivalLane="d-_0" arrivalPos="492.80" arrivalPosLat="0.00" arrivalSpeed="37.95" duration="43.89" routeLength="990.53" waitingTime="0.16" waitingCount="1" stopTime="0.00" timeLoss="-7.70" rerouteNo="0" devices="tripinfo_v1147.c_1" vType="vtypeauto" speedFactor="2.71" vaporized=""/>
    <tripinfo id="v1148.b_2" depart="3444.01" departLane="b+_0" departPos="4.10" departPosLat="0.00" departSpeed="0.00" departDelay="0.00" arrival="3492.68" arrivalLane="d-_0" arrivalPos="492.80" arrivalPosLat="0.00" arrivalSpeed="26.68" duration="48.67" routeLength="995.90" waitingTime="0.16" waitingCount="1" stopTime="0.00" timeLoss="-3.17" rerouteNo="0" devices="tripinfo_v1148.b_2" vType="vtypeauto" speedFactor="1.91" vaporized=""/>
    <tripinfo id="v1151.c_3" depart="3453.01" departLane="c+_0" departPos="4.10" departPosLat="0.00" departSpeed="0.00" departDelay="0.00" arrival="3497.16" arrivalLane="b-_0" arrivalPos="492.80" arrivalPosLat="0.00" arrivalSpeed="37.95" duration="44.15" routeLength="995.70" waitingTime="0.16" waitingCount="1" stopTime="0.00" timeLoss="-7.70" rerouteNo="0" devices="tripinfo_v1151.c_3" vType="vtypeauto" speedFactor="2.71" vaporized=""/>
    <tripinfo id="v1158.d_1" depart="3474.01" departLane="d+_0" departPos="4.10" departPosLat="0.00" departSpeed="0.00" departDelay="0.00" arrival="3517.90" arrivalLane="a-_0" arrivalPos="492.80" arrivalPosLat="0.00" arrivalSpeed="37.95" duration="43.89" routeLength="990.53" waitingTime="0.16" waitingCount="1" stopTime="0.00" timeLoss="-7.70" rerouteNo="0" devices="tripinfo_v1158.d_1" vType="vtypeauto" speedFactor="2.71" vaporized=""/>
    <tripinfo id="v1164.d_2" depart="3492.01" departLane="d+_0" departPos="4.10" departPosLat="0.00" departSpeed="0.00" departDelay="0.00" arrival="3536.17" arrivalLane="b-_0" arrivalPos="492.80" arrivalPosLat="0.00" arrivalSpeed="37.95" duration="44.16" routeLength="995.90" waitingTime="0.16" waitingCount="1" stopTime="0.00" timeLoss="-7.70" rerouteNo="0" devices="tripinfo_v1164.d_2" vType="vtypeauto" speedFactor="2.71" vaporized=""/>
    <tripinfo id="v1164.b_2" depart="3492.01" departLane="b+_0" departPos="4.10" departPosLat="0.00" departSpeed="0.00" departDelay="0.00" arrival="3536.17" arrivalLane="d-_0" arrivalPos="492.80" arrivalPosLat="0.00" arrivalSpeed="37.95" duration="44.16" routeLength="995.90" waitingTime="0.16" waitingCount="1" stopTime="0.00" timeLoss="-7.70" rerouteNo="0" devices="tripinfo_v1164.b_2" vType="vtypeauto" speedFactor="2.71" vaporized=""/>
    <tripinfo id="v1167.a_3" depart="3501.01" departLane="a+_0" departPos="4.10" departPosLat="0.00" departSpeed="0.00" departDelay="0.00" arrival="3545.51" arrivalLane="d-_0" arrivalPos="492.80" arrivalPosLat="0.00" arrivalSpeed="36.59" duration="44.50" routeLength="995.70" waitingTime="0.16" waitingCount="1" stopTime="0.00" timeLoss="-7.34" rerouteNo="0" devices="tripinfo_v1167.a_3" vType="vtypeauto" speedFactor="2.61" vaporized=""/>
    <tripinfo id="v1168.c_2" depart="3504.01" departLane="c+_0" departPos="4.10" departPosLat="0.00" departSpeed="0.00" departDelay="0.00" arrival="3548.17" arrivalLane="a-_0" arrivalPos="492.80" arrivalPosLat="0.00" arrivalSpeed="37.95" duration="44.16" routeLength="995.90" waitingTime="0.16" waitingCount="1" stopTime="0.00" timeLoss="-7.70" rerouteNo="0" devices="tripinfo_v1168.c_2" vType="vtypeauto" speedFactor="2.71" vaporized=""/>
    <tripinfo id="v1172.d_1" depart="3516.01" departLane="d+_0" departPos="4.10" departPosLat="0.00" departSpeed="0.00" departDelay="0.00" arrival="3559.90" arrivalLane="a-_0" arrivalPos="492.80" arrivalPosLat="0.00" arrivalSpeed="37.95" duration="43.89" routeLength="990.53" waitingTime="0.16" waitingCount="1" stopTime="0.00" timeLoss="-7.70" rerouteNo="0" devices="tripinfo_v1172.d_1" vType="vtypeauto" speedFactor="2.71" vaporized=""/>
    <tripinfo id="v1181.d_3" depart="3543.01" departLane="d+_0" departPos="4.10" departPosLat="0.00" departSpeed="0.00" departDelay="0.00" arrival="3587.16" arrivalLane="c-_0" arrivalPos="492.80" arrivalPosLat="0.00" arrivalSpeed="37.95" duration="44.15" routeLength="995.69" waitingTime="0.16" waitingCount="1" stopTime="0.00" timeLoss="-7.70" rerouteNo="0" devices="tripinfo_v1181.d_3" vType="vtypeauto" speedFactor="2.71" vaporized=""/>
    <tripinfo id="v1182.b_3" depart="3546.01" departLane="b+_0" departPos="4.10" departPosLat="0.00" departSpeed="0.00" departDelay="0.00" arrival="3590.16" arrivalLane="a-_0" arrivalPos="492.80" arrivalPosLat="0.00" arrivalSpeed="37.95" duration="44.15" routeLength="995.69" waitingTime="0.16" waitingCount="1" stopTime="0.00" timeLoss="-7.70" rerouteNo="0" devices="tripinfo_v1182.b_3" vType="vtypeauto" speedFactor="2.71" vaporized=""/>
</tripinfos>
